{"token":"3LqqYjEYQWQsrSk3Ypvy193fTspqZuiCy4emM7Bz","title":"learn anything - design - graphic design","backgroundColor":"rgba(243, 246, 243, 1.0)","nodes":[{"allowNodeStrokeColorVariants":false,"decreasingStrokeWidth":true,"foldedSubnodes":false,"isLeftAligned":false,"id":"4DE0A5D6-0014-4E8A-BCD8-104F33C25B07","pathStyle":{"lineType":"curved","strokeStyle":{"color":"rgba(21, 122, 150, 1.0)","dash":null,"width":4.0}},"shapeStyle":{"fillColor":"rgba(255, 255, 255, 1.0)","shapeType":"roundedrect","borderStrokeStyle":{"color":"rgba(246, 246, 246, 1.0)","dash":null,"width":2.0}},"image":null,"title":{"allowToShrinkWidth":true,"maxWidth":300.0,"text":"\u003cp style=\"text-align: center; \"\u003e\u003ca style='color: rgba(22, 103, 132, 1.000000); font: 21px \"Helvetica Neue\";  ' href=\"http://www.wikiwand.com/en/Graphic_design\" rel=\"nofollow\"\u003egraphic design \u003c/a\u003e\u003ca style='color: rgba(22, 103, 132, 1.000000); font: 21px \"Apple Color Emoji\";  ' href=\"http://www.wikiwand.com/en/Graphic_design\" rel=\"nofollow\"\u003e🌐\u003c/a\u003e\u003c/p\u003e","fontStyle":null},"note":null,"noteIndicatorColor":"rgba(0, 0, 0, 1.0)","nodes":[{"allowNodeStrokeColorVariants":false,"decreasingStrokeWidth":false,"foldedSubnodes":false,"isLeftAligned":false,"id":"C16D5B81-9AFC-49B9-AB26-BDC34F953863","pathStyle":{"lineType":"curved","strokeStyle":{"color":"rgba(36, 170, 255, 1.0)","dash":null,"width":6.0}},"shapeStyle":{"fillColor":"rgba(255, 255, 255, 1.0)","shapeType":null,"borderStrokeStyle":{"color":"rgba(36, 170, 255, 1.0)","dash":null,"width":2.0}},"image":null,"title":{"allowToShrinkWidth":true,"maxWidth":300.0,"text":"\u003cp style='color: rgba(72, 72, 72, 1.000000); font: 18px \"Apple Color Emoji\"; text-align: left;  '\u003e\u003ca href=\"https://www.reddit.com/r/graphic_design/\" rel=\"nofollow\"\u003e🤖\u003c/a\u003e\u003c/p\u003e","fontStyle":null},"note":null,"noteIndicatorColor":"rgba(0, 0, 0, 1.0)","nodes":[],"location":{"x":185.30000000000007,"y":-204.79375},"layoutStyle":"manual","task":null},{"allowNodeStrokeColorVariants":false,"decreasingStrokeWidth":false,"foldedSubnodes":false,"isLeftAligned":false,"id":"837A5426-4B9E-4456-A60D-B8EF906287A0","pathStyle":{"lineType":"curved","strokeStyle":{"color":"rgba(175, 54, 242, 1.0)","dash":null,"width":6.0}},"shapeStyle":{"fillColor":"rgba(255, 255, 255, 1.0)","shapeType":null,"borderStrokeStyle":{"color":"rgba(175, 54, 242, 1.0)","dash":null,"width":2.0}},"image":null,"title":{"allowToShrinkWidth":true,"maxWidth":300.0,"text":"\u003cp style=\"text-align: left; \"\u003e\u003ca style='color: rgba(72, 72, 72, 1.000000); font: 18px \"Helvetica Neue\";  ' href=\"https://graphicdesign.stackexchange.com/\" rel=\"nofollow\"\u003e \u003c/a\u003e\u003ca style='color: rgba(72, 72, 72, 1.000000); font: 18px \"Apple Color Emoji\";  ' href=\"https://graphicdesign.stackexchange.com/\" rel=\"nofollow\"\u003e🗂️\u003c/a\u003e\u003c/p\u003e","fontStyle":null},"note":null,"noteIndicatorColor":"rgba(0, 0, 0, 1.0)","nodes":[],"location":{"x":185.30000000000007,"y":-164.79375},"layoutStyle":"manual","task":null}],"location":{"x":-73.69999999999993,"y":-198.79375},"layoutStyle":"defaultright","task":null},{"allowNodeStrokeColorVariants":false,"decreasingStrokeWidth":true,"foldedSubnodes":false,"isLeftAligned":false,"id":"D08883B7-ECBD-48C4-B512-904F8E172EEA","pathStyle":{"lineType":"curved","strokeStyle":{"color":"rgba(21, 122, 150, 1.0)","dash":null,"width":4.0}},"shapeStyle":{"fillColor":"rgba(255, 255, 255, 1.0)","shapeType":"roundedrect","borderStrokeStyle":{"color":"rgba(246, 246, 246, 1.0)","dash":null,"width":2.0}},"image":null,"title":{"allowToShrinkWidth":true,"maxWidth":300.0,"text":"\u003cp style='color: rgba(22, 103, 132, 1.000000); font: 21px \"Helvetica Neue\"; text-align: center;  '\u003ebasics\u003c/p\u003e","fontStyle":null},"note":{"visibleOnCanvas":false,"text":"\u003cp style='color: rgba(0, 0, 0, 1.000000); font: 15px \"Helvetica Neue\";  '\u003eif you think this can be improved in any way\u003c/p\u003e\u003cp\u003e\u003c/p\u003e\u003cp\u003e\u003ca style='color: rgba(0, 0, 0, 1.000000); font: 15px \"Helvetica Neue\";  ' href=\"https://github.com/nikitavoloboev/knowledge-map/issues/631\" rel=\"nofollow\"\u003eplease say\u003c/a\u003e\u003cspan style='color: rgba(0, 0, 0, 1.000000); font: 15px \"Helvetica Neue\";  '\u003e \u003c/span\u003e\u003cspan style='color: rgba(0, 0, 0, 1.000000); font: 15px \"Apple Color Emoji\";  '\u003e💙\u003c/span\u003e\u003c/p\u003e"},"noteIndicatorColor":"rgba(21, 122, 150, 1.0)","nodes":[{"allowNodeStrokeColorVariants":false,"decreasingStrokeWidth":false,"foldedSubnodes":false,"isLeftAligned":false,"id":"9FBC8237-BED3-4B7D-B9E4-3428CE4DBCFF","pathStyle":{"lineType":"curved","strokeStyle":{"color":"rgba(36, 170, 255, 1.0)","dash":null,"width":6.0}},"shapeStyle":{"fillColor":"rgba(255, 255, 255, 1.0)","shapeType":null,"borderStrokeStyle":{"color":"rgba(36, 170, 255, 1.0)","dash":null,"width":2.0}},"image":null,"title":{"allowToShrinkWidth":true,"maxWidth":300.0,"text":"\u003cp style=\"text-align: left; \"\u003e\u003ca style='color: rgba(73, 73, 73, 1.000000); font: 18px \"Helvetica Neue\";  ' href=\"https://www.youtube.com/watch?v=WONZVnlam6U\u0026amp;list=PLYfCBK8IplO4E2sXtdKMVpKJZRBEoMvpn\" rel=\"nofollow\"\u003e1. beginners guide to graphic design \u003c/a\u003e\u003ca style='color: rgba(73, 73, 73, 1.000000); font: 18px \"Apple Color Emoji\";  ' href=\"https://www.youtube.com/watch?v=WONZVnlam6U\u0026amp;list=PLYfCBK8IplO4E2sXtdKMVpKJZRBEoMvpn\" rel=\"nofollow\"\u003e👀\u003c/a\u003e\u003c/p\u003e","fontStyle":null},"note":null,"noteIndicatorColor":"rgba(0, 0, 0, 1.0)","nodes":[],"location":{"x":148.38041639328003,"y":-69.48576545715332},"layoutStyle":"manual","task":null},{"allowNodeStrokeColorVariants":false,"decreasingStrokeWidth":false,"foldedSubnodes":false,"isLeftAligned":false,"id":"52BA3156-7474-4B5C-93A8-12284BA8E86B","pathStyle":{"lineType":"curved","strokeStyle":{"color":"rgba(175, 54, 242, 1.0)","dash":null,"width":6.0}},"shapeStyle":{"fillColor":"rgba(255, 255, 255, 1.0)","shapeType":null,"borderStrokeStyle":{"color":"rgba(175, 54, 242, 1.0)","dash":null,"width":2.0}},"image":null,"title":{"allowToShrinkWidth":true,"maxWidth":300.0,"text":"\u003cp style=\"text-align: left; \"\u003e\u003ca style='color: rgba(72, 72, 72, 1.000000); font: 18px \"Helvetica Neue\";  ' href=\"https://www.goodreads.com/book/show/44735.The_Elements_of_Typographic_Style\" rel=\"nofollow\"\u003e2. elements of typographic style \u003c/a\u003e\u003ca style='color: rgba(72, 72, 72, 1.000000); font: 18px \"Apple Color Emoji\";  ' href=\"https://www.goodreads.com/book/show/44735.The_Elements_of_Typographic_Style\" rel=\"nofollow\"\u003e📕\u003c/a\u003e\u003c/p\u003e","fontStyle":null},"note":null,"noteIndicatorColor":"rgba(0, 0, 0, 1.0)","nodes":[],"location":{"x":148.38041639328003,"y":-7.48576545715332},"layoutStyle":"manual","task":null}],"location":{"x":-33.61958360671997,"y":-49.98576545715332},"layoutStyle":"defaultright","task":null},{"allowNodeStrokeColorVariants":false,"decreasingStrokeWidth":true,"foldedSubnodes":false,"isLeftAligned":false,"id":"E39D4E80-0A4D-40BE-8D5E-987E7445D949","pathStyle":{"lineType":"curved","strokeStyle":{"color":"rgba(21, 122, 150, 1.0)","dash":null,"width":4.0}},"shapeStyle":{"fillColor":"rgba(255, 255, 255, 1.0)","shapeType":"roundedrect","borderStrokeStyle":{"color":"rgba(246, 246, 246, 1.0)","dash":null,"width":2.0}},"image":null,"title":{"allowToShrinkWidth":true,"maxWidth":300.0,"text":"\u003cp style='color: rgba(22, 103, 132, 1.000000); font: 21px \"Helvetica Neue\"; text-align: center;  '\u003einteresting\u003c/p\u003e","fontStyle":null},"note":null,"noteIndicatorColor":"rgba(0, 0, 0, 1.0)","nodes":[{"allowNodeStrokeColorVariants":false,"decreasingStrokeWidth":false,"foldedSubnodes":false,"isLeftAligned":false,"id":"C65FE0FB-BAFB-45F9-A827-6FB1152899D3","pathStyle":{"lineType":"curved","strokeStyle":{"color":"rgba(175, 54, 242, 1.0)","dash":null,"width":6.0}},"shapeStyle":{"fillColor":"rgba(255, 255, 255, 1.0)","shapeType":null,"borderStrokeStyle":{"color":"rgba(175, 54, 242, 1.0)","dash":null,"width":2.0}},"image":null,"title":{"allowToShrinkWidth":true,"maxWidth":300.0,"text":"\u003cp style=\"text-align: left; \"\u003e\u003ca style='color: rgba(73, 73, 73, 1.000000); font: 18px \"Helvetica Neue\";  ' href=\"https://imgur.com/a/4scqU\" rel=\"nofollow\"\u003evector icon speed runs \u003c/a\u003e\u003ca style='color: rgba(73, 73, 73, 1.000000); font: 18px \"Apple Color Emoji\";  ' href=\"https://imgur.com/a/4scqU\" rel=\"nofollow\"\u003e🖌\u003c/a\u003e\u003c/p\u003e","fontStyle":null},"note":null,"noteIndicatorColor":"rgba(0, 0, 0, 1.0)","nodes":[],"location":{"x":297.134381866455,"y":86.69810409545903},"layoutStyle":"manual","task":null}],"location":{"x":106.13438186645499,"y":75.19810409545903},"layoutStyle":"defaultright","task":null},{"allowNodeStrokeColorVariants":false,"decreasingStrokeWidth":true,"foldedSubnodes":false,"isLeftAligned":false,"id":"AD2D3994-1C2E-4EF8-B217-570641D988FB","pathStyle":{"lineType":"curved","strokeStyle":{"color":"rgba(21, 122, 150, 1.0)","dash":null,"width":4.0}},"shapeStyle":{"fillColor":"rgba(255, 255, 255, 1.0)","shapeType":"roundedrect","borderStrokeStyle":{"color":"rgba(246, 246, 246, 1.0)","dash":null,"width":2.0}},"image":null,"title":{"allowToShrinkWidth":true,"maxWidth":300.0,"text":"\u003cp style=\"text-align: center; \"\u003e\u003ca style='color: rgba(22, 103, 132, 1.000000); font: 21px \"Helvetica Neue\";  ' href=\"/id/Bq15VPP9eVsmunFsM9RAFjpawSsgpuCBSi9ou3ye\" rel=\"nofollow\"\u003ephotoshop \u003c/a\u003e\u003ca style='color: rgba(22, 103, 132, 1.000000); font: 21px \"Apple Color Emoji\";  ' href=\"/id/Bq15VPP9eVsmunFsM9RAFjpawSsgpuCBSi9ou3ye\" rel=\"nofollow\"\u003e🗺️\u003c/a\u003e\u003c/p\u003e","fontStyle":null},"note":null,"noteIndicatorColor":"rgba(0, 0, 0, 1.0)","nodes":[],"location":{"x":-160.2972472685925,"y":159.18196473234673},"layoutStyle":"defaultright","task":null},{"allowNodeStrokeColorVariants":false,"decreasingStrokeWidth":true,"foldedSubnodes":false,"isLeftAligned":false,"id":"B5803728-13C4-4D56-8ED5-A7CF1AD36C6E","pathStyle":{"lineType":"curved","strokeStyle":{"color":"rgba(21, 122, 150, 1.0)","dash":null,"width":4.0}},"shapeStyle":{"fillColor":"rgba(255, 255, 255, 1.0)","shapeType":"roundedrect","borderStrokeStyle":{"color":"rgba(246, 246, 246, 1.0)","dash":null,"width":2.0}},"image":null,"title":{"allowToShrinkWidth":true,"maxWidth":300.0,"text":"\u003cp style=\"text-align: center; \"\u003e\u003ca style='color: rgba(22, 103, 132, 1.000000); font: 21px \"Helvetica Neue\";  ' href=\"/id/RSXm2uqj7zPPtpvzfqdxqLpkbptB3yg5s6koUexs\" rel=\"nofollow\"\u003esketch \u003c/a\u003e\u003ca style='color: rgba(22, 103, 132, 1.000000); font: 21px \"Apple Color Emoji\";  ' href=\"/id/RSXm2uqj7zPPtpvzfqdxqLpkbptB3yg5s6koUexs\" rel=\"nofollow\"\u003e🗺️\u003c/a\u003e\u003c/p\u003e","fontStyle":null},"note":null,"noteIndicatorColor":"rgba(0, 0, 0, 1.0)","nodes":[],"location":{"x":26.942776892090137,"y":159.73367585155245},"layoutStyle":"defaultright","task":null},{"allowNodeStrokeColorVariants":false,"decreasingStrokeWidth":true,"foldedSubnodes":false,"isLeftAligned":false,"id":"CD8CF2B6-890E-4F6C-BEE6-3D99960716EC","pathStyle":{"lineType":"curved","strokeStyle":{"color":"rgba(21, 122, 150, 1.0)","dash":null,"width":4.0}},"shapeStyle":{"fillColor":"rgba(255, 255, 255, 1.0)","shapeType":"roundedrect","borderStrokeStyle":{"color":"rgba(246, 246, 246, 1.0)","dash":null,"width":2.0}},"image":null,"title":{"allowToShrinkWidth":true,"maxWidth":300.0,"text":"\u003cp style=\"text-align: center; \"\u003e\u003ca style='color: rgba(22, 103, 132, 1.000000); font: 21px \"Helvetica Neue\";  ' href=\"/id/s8pqMXQviFER3HQHDpWWeGsv7fTN3BBerWQezgJH\" rel=\"nofollow\"\u003eadobe illustrator \u003c/a\u003e\u003ca style='color: rgba(22, 103, 132, 1.000000); font: 21px \"Apple Color Emoji\";  ' href=\"/id/s8pqMXQviFER3HQHDpWWeGsv7fTN3BBerWQezgJH\" rel=\"nofollow\"\u003e🗺️\u003c/a\u003e\u003c/p\u003e","fontStyle":null},"note":null,"noteIndicatorColor":"rgba(0, 0, 0, 1.0)","nodes":[],"location":{"x":-387.23923365724386,"y":161.69959143109543},"layoutStyle":"defaultright","task":null}],"connections":[{"endNodeID":"D08883B7-ECBD-48C4-B512-904F8E172EEA","startNodeID":"4DE0A5D6-0014-4E8A-BCD8-104F33C25B07","pathStyle":{"lineType":"curved","strokeStyle":{"color":"rgba(254, 90, 46, 1.0)","dash":[5,2],"width":2.0}},"arrowStyle":{"startArrow":null,"endArrow":"trianglefilled"},"title":{"allowToShrinkWidth":true,"maxWidth":250.0,"text":"","fontStyle":{"bold":false,"italic":false,"underline":false,"strikethrough":false,"color":"rgba(255, 255, 255, 1.0)","fontName":"HelveticaNeue","fontSize":14,"alignment":"center"}},"wayPointOffset":{"x":-5.95979,"y":73.1539}},{"endNodeID":"B5803728-13C4-4D56-8ED5-A7CF1AD36C6E","startNodeID":"D08883B7-ECBD-48C4-B512-904F8E172EEA","pathStyle":{"lineType":"curved","strokeStyle":{"color":"rgba(254, 90, 46, 1.0)","dash":[5,2],"width":2.0}},"arrowStyle":{"startArrow":null,"endArrow":"trianglefilled"},"title":{"allowToShrinkWidth":true,"maxWidth":250.0,"text":"","fontStyle":{"bold":false,"italic":false,"underline":false,"strikethrough":false,"color":"rgba(255, 255, 255, 1.0)","fontName":"HelveticaNeue","fontSize":14,"alignment":"center"}},"wayPointOffset":{"x":30.7811,"y":104.86}},{"endNodeID":"AD2D3994-1C2E-4EF8-B217-570641D988FB","startNodeID":"D08883B7-ECBD-48C4-B512-904F8E172EEA","pathStyle":{"lineType":"curved","strokeStyle":{"color":"rgba(254, 90, 46, 1.0)","dash":[5,2],"width":2.0}},"arrowStyle":{"startArrow":null,"endArrow":"trianglefilled"},"title":{"allowToShrinkWidth":true,"maxWidth":250.0,"text":"","fontStyle":{"bold":false,"italic":false,"underline":false,"strikethrough":false,"color":"rgba(255, 255, 255, 1.0)","fontName":"HelveticaNeue","fontSize":14,"alignment":"center"}},"wayPointOffset":{"x":-59.5893,"y":104.584}},{"endNodeID":"D08883B7-ECBD-48C4-B512-904F8E172EEA","startNodeID":"E39D4E80-0A4D-40BE-8D5E-987E7445D949","pathStyle":{"lineType":"curved","strokeStyle":{"color":"rgba(254, 90, 46, 1.0)","dash":[5,2],"width":2.0}},"arrowStyle":{"startArrow":null,"endArrow":"trianglefilled"},"title":{"allowToShrinkWidth":true,"maxWidth":250.0,"text":"","fontStyle":{"bold":false,"italic":false,"underline":false,"strikethrough":false,"color":"rgba(255, 255, 255, 1.0)","fontName":"HelveticaNeue","fontSize":14,"alignment":"center"}},"wayPointOffset":{"x":-72.127,"y":-62.592}},{"endNodeID":"CD8CF2B6-890E-4F6C-BEE6-3D99960716EC","startNodeID":"D08883B7-ECBD-48C4-B512-904F8E172EEA","pathStyle":{"lineType":"curved","strokeStyle":{"color":"rgba(254, 90, 46, 1.0)","dash":[5,2],"width":2.0}},"arrowStyle":{"startArrow":null,"endArrow":"trianglefilled"},"title":{"allowToShrinkWidth":true,"maxWidth":250.0,"text":"","fontStyle":{"bold":false,"italic":false,"underline":false,"strikethrough":false,"color":"rgba(255, 255, 255, 1.0)","fontName":"HelveticaNeue","fontSize":14,"alignment":"left"}},"wayPointOffset":{"x":-197.572,"y":105.23}}],"ready":true}