{"token":"psD7CyDsn1PnCNq8xpxK9983oC4nDSYGbN7xUJJ8","title":"learn anything - software - tooling - spreadsheets - excel","backgroundColor":"rgba(243, 246, 243, 1.0)","nodes":[{"allowNodeStrokeColorVariants":false,"decreasingStrokeWidth":true,"foldedSubnodes":false,"isLeftAligned":false,"id":"58012125-1839-4BF2-AFCA-D6B97D222AEB","pathStyle":{"lineType":"curved","strokeStyle":{"color":"rgba(21, 122, 150, 1.0)","dash":null,"width":4.0}},"shapeStyle":{"fillColor":"rgba(255, 255, 255, 1.0)","shapeType":"roundedrect","borderStrokeStyle":{"color":"rgba(246, 246, 246, 1.0)","dash":null,"width":2.0}},"image":null,"title":{"allowToShrinkWidth":true,"maxWidth":300.0,"text":"\u003cp style=\"text-align: center; \"\u003e\u003ca style='color: rgba(22, 103, 132, 1.000000); font: 21px \"Helvetica Neue\";  ' href=\"http://www.wikiwand.com/en/Microsoft_Excel\" rel=\"nofollow\"\u003emicrosoft excel \u003c/a\u003e\u003ca style='color: rgba(22, 103, 132, 1.000000); font: 21px \"Apple Color Emoji\";  ' href=\"http://www.wikiwand.com/en/Microsoft_Excel\" rel=\"nofollow\"\u003e🌐\u003c/a\u003e\u003c/p\u003e","fontStyle":null},"note":null,"noteIndicatorColor":"rgba(0, 0, 0, 1.0)","nodes":[{"allowNodeStrokeColorVariants":false,"decreasingStrokeWidth":false,"foldedSubnodes":false,"isLeftAligned":false,"id":"E0776060-1F0B-4F04-BA57-533F2DCF36C0","pathStyle":{"lineType":"curved","strokeStyle":{"color":"rgba(175, 54, 242, 1.0)","dash":null,"width":6.0}},"shapeStyle":{"fillColor":"rgba(255, 255, 255, 1.0)","shapeType":null,"borderStrokeStyle":{"color":"rgba(175, 54, 242, 1.0)","dash":null,"width":2.0}},"image":null,"title":{"allowToShrinkWidth":true,"maxWidth":300.0,"text":"\u003cp style='color: rgba(72, 72, 72, 1.000000); font: 18px \"Apple Color Emoji\"; text-align: left;  '\u003e\u003ca href=\"https://www.reddit.com/r/excel/\" rel=\"nofollow\"\u003e🤖\u003c/a\u003e\u003c/p\u003e","fontStyle":null},"note":null,"noteIndicatorColor":"rgba(0, 0, 0, 1.0)","nodes":[],"location":{"x":181.91796875,"y":-258.31640625},"layoutStyle":"manual","task":null}],"location":{"x":-81.08203125,"y":-272.31640625},"layoutStyle":"defaultright","task":null},{"allowNodeStrokeColorVariants":false,"decreasingStrokeWidth":true,"foldedSubnodes":false,"isLeftAligned":false,"id":"74D1081B-ECB6-40C6-9CB7-C57541B97821","pathStyle":{"lineType":"curved","strokeStyle":{"color":"rgba(21, 122, 150, 1.0)","dash":null,"width":4.0}},"shapeStyle":{"fillColor":"rgba(255, 255, 255, 1.0)","shapeType":"roundedrect","borderStrokeStyle":{"color":"rgba(246, 246, 246, 1.0)","dash":null,"width":2.0}},"image":null,"title":{"allowToShrinkWidth":true,"maxWidth":300.0,"text":"\u003cp style='color: rgba(22, 103, 132, 1.000000); font: 21px \"Helvetica Neue\"; text-align: center;  '\u003ehelp\u003c/p\u003e","fontStyle":null},"note":null,"noteIndicatorColor":"rgba(0, 0, 0, 1.0)","nodes":[{"allowNodeStrokeColorVariants":false,"decreasingStrokeWidth":false,"foldedSubnodes":false,"isLeftAligned":false,"id":"6CCC0C13-9380-4B8A-B035-B47C6AB761B5","pathStyle":{"lineType":"curved","strokeStyle":{"color":"rgba(175, 54, 242, 1.0)","dash":null,"width":6.0}},"shapeStyle":{"fillColor":"rgba(255, 255, 255, 1.0)","shapeType":null,"borderStrokeStyle":{"color":"rgba(175, 54, 242, 1.0)","dash":null,"width":2.0}},"image":null,"title":{"allowToShrinkWidth":true,"maxWidth":300.0,"text":"\u003cp style=\"text-align: left; \"\u003e\u003ca style='color: rgba(72, 72, 72, 1.000000); font: 18px \"Helvetica Neue\";  ' href=\"https://www.youtube.com/user/ExcelIsFun/videos\" rel=\"nofollow\"\u003eexcel is fun \u003c/a\u003e\u003ca style='color: rgba(72, 72, 72, 1.000000); font: 18px \"Apple Color Emoji\";  ' href=\"https://www.youtube.com/user/ExcelIsFun/videos\" rel=\"nofollow\"\u003e🎥\u003c/a\u003e\u003c/p\u003e","fontStyle":null},"note":null,"noteIndicatorColor":"rgba(0, 0, 0, 1.0)","nodes":[],"location":{"x":192.42280837271335,"y":-165.75471608808925},"layoutStyle":"manual","task":null},{"allowNodeStrokeColorVariants":false,"decreasingStrokeWidth":false,"foldedSubnodes":false,"isLeftAligned":false,"id":"4C8BBC76-99A6-4C1C-9908-5D0220654628","pathStyle":{"lineType":"curved","strokeStyle":{"color":"rgba(36, 170, 255, 1.0)","dash":null,"width":6.0}},"shapeStyle":{"fillColor":"rgba(255, 255, 255, 1.0)","shapeType":null,"borderStrokeStyle":{"color":"rgba(36, 170, 255, 1.0)","dash":null,"width":2.0}},"image":null,"title":{"allowToShrinkWidth":true,"maxWidth":300.0,"text":"\u003cp style='color: rgba(72, 72, 72, 1.000000); font: 18px \"Helvetica Neue\"; text-align: left;  '\u003e\u003ca href=\"https://www.techonthenet.com/excel/formulas/\" rel=\"nofollow\"\u003eexcel functions\u003c/a\u003e\u003c/p\u003e","fontStyle":null},"note":null,"noteIndicatorColor":"rgba(0, 0, 0, 1.0)","nodes":[],"location":{"x":192.42280837271335,"y":-125.75471608808925},"layoutStyle":"manual","task":null}],"location":{"x":55.42280837271335,"y":-160.25471608808925},"layoutStyle":"defaultright","task":null},{"allowNodeStrokeColorVariants":false,"decreasingStrokeWidth":true,"foldedSubnodes":false,"isLeftAligned":false,"id":"E1990EF5-DB94-4B89-8879-C22B8F6C99C5","pathStyle":{"lineType":"curved","strokeStyle":{"color":"rgba(21, 122, 150, 1.0)","dash":null,"width":4.0}},"shapeStyle":{"fillColor":"rgba(255, 255, 255, 1.0)","shapeType":"roundedrect","borderStrokeStyle":{"color":"rgba(246, 246, 246, 1.0)","dash":null,"width":2.0}},"image":null,"title":{"allowToShrinkWidth":true,"maxWidth":300.0,"text":"\u003cp style='color: rgba(22, 103, 132, 1.000000); font: 21px \"Helvetica Neue\"; text-align: center;  '\u003einteresting\u003c/p\u003e","fontStyle":null},"note":null,"noteIndicatorColor":"rgba(0, 0, 0, 1.0)","nodes":[{"allowNodeStrokeColorVariants":false,"decreasingStrokeWidth":false,"foldedSubnodes":false,"isLeftAligned":false,"id":"B960AB8B-A59B-47E2-8097-D387AD2A1862","pathStyle":{"lineType":"curved","strokeStyle":{"color":"rgba(175, 54, 242, 1.0)","dash":null,"width":6.0}},"shapeStyle":{"fillColor":"rgba(255, 255, 255, 1.0)","shapeType":null,"borderStrokeStyle":{"color":"rgba(175, 54, 242, 1.0)","dash":null,"width":2.0}},"image":null,"title":{"allowToShrinkWidth":true,"maxWidth":300.0,"text":"\u003cp style=\"text-align: left; \"\u003e\u003ca style='color: rgba(72, 72, 72, 1.000000); font: 18px \"Helvetica Neue\";  ' href=\"https://www.youtube.com/watch?v=0nbkaYsR94c\" rel=\"nofollow\"\u003e15: you suck at excel with Joel Spolsky \u003c/a\u003e\u003ca style='color: rgba(72, 72, 72, 1.000000); font: 18px \"Apple Color Emoji\";  ' href=\"https://www.youtube.com/watch?v=0nbkaYsR94c\" rel=\"nofollow\"\u003e👀\u003c/a\u003e\u003c/p\u003e","fontStyle":null},"note":null,"noteIndicatorColor":"rgba(0, 0, 0, 1.0)","nodes":[],"location":{"x":294.1506819346595,"y":-57.32941652227328},"layoutStyle":"manual","task":null}],"location":{"x":103.15068193465947,"y":-57.82941652227328},"layoutStyle":"defaultright","task":null},{"allowNodeStrokeColorVariants":false,"decreasingStrokeWidth":true,"foldedSubnodes":false,"isLeftAligned":false,"id":"7D635641-2FE4-4F44-99D0-F34AE53C5F32","pathStyle":{"lineType":"curved","strokeStyle":{"color":"rgba(21, 122, 150, 1.0)","dash":null,"width":4.0}},"shapeStyle":{"fillColor":"rgba(255, 255, 255, 1.0)","shapeType":"roundedrect","borderStrokeStyle":{"color":"rgba(246, 246, 246, 1.0)","dash":null,"width":2.0}},"image":null,"title":{"allowToShrinkWidth":true,"maxWidth":300.0,"text":"\u003cp style='color: rgba(22, 103, 132, 1.000000); font: 21px \"Helvetica Neue\"; text-align: center;  '\u003ebasics\u003c/p\u003e","fontStyle":null},"note":{"visibleOnCanvas":false,"text":"\u003cp style='color: rgba(0, 0, 0, 1.000000); font: 15px \"Helvetica Neue\";  '\u003eif you think this can be improved in any way\u003c/p\u003e\u003cp\u003e\u003c/p\u003e\u003cp\u003e\u003ca style='color: rgba(0, 0, 0, 1.000000); font: 15px \"Helvetica Neue\";  ' href=\"https://github.com/nikitavoloboev/learn-anything/issues/1035\" rel=\"nofollow\"\u003eplease say\u003c/a\u003e\u003cspan style='color: rgba(0, 0, 0, 1.000000); font: 15px \"Helvetica Neue\";  '\u003e \u003c/span\u003e\u003cspan style='color: rgba(0, 0, 0, 1.000000); font: 15px \"Apple Color Emoji\";  '\u003e💙\u003c/span\u003e\u003c/p\u003e"},"noteIndicatorColor":"rgba(21, 122, 150, 1.0)","nodes":[{"allowNodeStrokeColorVariants":false,"decreasingStrokeWidth":false,"foldedSubnodes":false,"isLeftAligned":false,"id":"A1765849-5421-46EF-89F5-27F32E81BFEE","pathStyle":{"lineType":"curved","strokeStyle":{"color":"rgba(175, 54, 242, 1.0)","dash":null,"width":6.0}},"shapeStyle":{"fillColor":"rgba(255, 255, 255, 1.0)","shapeType":null,"borderStrokeStyle":{"color":"rgba(175, 54, 242, 1.0)","dash":null,"width":2.0}},"image":null,"title":{"allowToShrinkWidth":true,"maxWidth":300.0,"text":"\u003cp style=\"text-align: left; \"\u003e\u003ca style='color: rgba(72, 72, 72, 1.000000); font: 18px \"Helvetica Neue\";  ' href=\"https://www.udemy.com/tutorials/learn-excel/\" rel=\"nofollow\"\u003e1. learn excel \u003c/a\u003e\u003ca style='color: rgba(72, 72, 72, 1.000000); font: 18px \"Apple Color Emoji\";  ' href=\"https://www.udemy.com/tutorials/learn-excel/\" rel=\"nofollow\"\u003e📝\u003c/a\u003e\u003c/p\u003e","fontStyle":null},"note":null,"noteIndicatorColor":"rgba(0, 0, 0, 1.0)","nodes":[],"location":{"x":147.3953885931187,"y":52.64468687552005},"layoutStyle":"manual","task":null}],"location":{"x":-34.604611406881304,"y":41.14468687552005},"layoutStyle":"defaultright","task":null}],"connections":[{"endNodeID":"58012125-1839-4BF2-AFCA-D6B97D222AEB","startNodeID":"74D1081B-ECB6-40C6-9CB7-C57541B97821","pathStyle":{"lineType":"curved","strokeStyle":{"color":"rgba(254, 90, 46, 1.0)","dash":[5,2],"width":2.0}},"arrowStyle":{"startArrow":null,"endArrow":"trianglefilled"},"title":{"allowToShrinkWidth":true,"maxWidth":250.0,"text":"","fontStyle":{"bold":false,"italic":false,"underline":false,"strikethrough":false,"color":"rgba(255, 255, 255, 1.0)","fontName":"HelveticaNeue","fontSize":14,"alignment":"left"}},"wayPointOffset":{"x":-36.7524,"y":-54.7808}},{"endNodeID":"74D1081B-ECB6-40C6-9CB7-C57541B97821","startNodeID":"E1990EF5-DB94-4B89-8879-C22B8F6C99C5","pathStyle":{"lineType":"curved","strokeStyle":{"color":"rgba(254, 90, 46, 1.0)","dash":[5,2],"width":2.0}},"arrowStyle":{"startArrow":null,"endArrow":"trianglefilled"},"title":{"allowToShrinkWidth":true,"maxWidth":250.0,"text":"","fontStyle":{"bold":false,"italic":false,"underline":false,"strikethrough":false,"color":"rgba(255, 255, 255, 1.0)","fontName":"HelveticaNeue","fontSize":14,"alignment":"left"}},"wayPointOffset":{"x":-37.3639,"y":-51.2126}},{"endNodeID":"7D635641-2FE4-4F44-99D0-F34AE53C5F32","startNodeID":"58012125-1839-4BF2-AFCA-D6B97D222AEB","pathStyle":{"lineType":"curved","strokeStyle":{"color":"rgba(254, 90, 46, 1.0)","dash":[5,2],"width":2.0}},"arrowStyle":{"startArrow":null,"endArrow":"trianglefilled"},"title":{"allowToShrinkWidth":true,"maxWidth":250.0,"text":"","fontStyle":{"bold":false,"italic":false,"underline":false,"strikethrough":false,"color":"rgba(255, 255, 255, 1.0)","fontName":"HelveticaNeue","fontSize":14,"alignment":"left"}},"wayPointOffset":{"x":-3.51129,"y":155.481}}],"ready":true}