{
  "title": "learn anything - databases - nosql databases - cassandra",
  "tag": "apache cassandra",
  "id": 405,
  "map": {
    "text": "Cassandra",
    "nodes": [
      {
        "text": "Basics",
        "note": "",
        "nodes": [],
        "resources": [
          {
            "url": "https://academy.datastax.com/resources/ds201-foundations-apache-cassandra",
            "text": "Foundations of apache cassandra",
            "category": "course",
            "note": "",
            "author": "",
            "score": {
              "up": 0,
              "down": 0
            }
          }
        ],
        "author": ""
      },
      {
        "text": "Help",
        "nodes": [],
        "resources": [
          {
            "url": "https://github.com/yikebocai/awesome-cassandra",
            "text": "Awesome cassandra",
            "category": "github",
            "note": "",
            "author": "",
            "score": {
              "up": 0,
              "down": 0
            }
          }
        ],
        "author": ""
      }
    ],
    "resources": [
      {
        "url": "https://github.com/apache/cassandra",
        "text": "Apache/cassandra",
        "category": "github",
        "note": "",
        "author": "",
        "score": {
          "up": 0,
          "down": 0
        }
      },
      {
        "url": "http://www.wikiwand.com/en/Apache_Cassandra",
        "text": "Cassandra",
        "category": "wiki",
        "note": "",
        "author": "",
        "score": {
          "up": 0,
          "down": 0
        }
      }
    ],
    "author": ""
  }
}