{
  "title": "learn anything - mathematics - logic - categorical logic",
  "tag": "",
  "id": 1001,
  "map": {
    "text": "categorical logic",
    "nodes": [
      {
        "text": "basics",
        "nodes": [],
        "resources": [
          {
            "url": "https://www.youtube.com/playlist?annotation_id=annotation_4184141781&amp;feature=iv&amp;list=PLz0n_SjOttTcESSCIAzDG1UoJlyjjR0bq&amp;src_vid=YxBShJU_CKs",
            "text": "1. video series",
            "category": "video",
            "note": "",
            "author": "",
            "score": {
              "up": 0,
              "down": 0
            }
          }
        ],
        "author": ""
      }
    ],
    "resources": [
      {
        "url": "http://www.wikiwand.com/en/Categorical_logic",
        "text": "categorical logic",
        "category": "wiki",
        "note": "",
        "author": "",
        "score": {
          "up": 0,
          "down": 0
        }
      }
    ],
    "author": ""
  }
}