{
  "title": "learn anything - physics - particle physics - elementary particles",
  "tag": "",
  "id": 1514,
  "map": {
    "text": "elementary particles",
    "nodes": [
      {
        "text": "basics",
        "nodes": [
          {
            "text": "photons  ️",
            "nodes": [],
            "resources": [
              {
                "url": "/physics/particle-physics/elementary-particles/photons",
                "text": "photons  ️",
                "category": "mindmap",
                "note": "",
                "author": "",
                "score": {
                  "up": 0,
                  "down": 0
                }
              }
            ],
            "author": ""
          },
          {
            "text": "leptons  ️",
            "nodes": [],
            "resources": [
              {
                "url": "/physics/particle-physics/elementary-particles/leptons",
                "text": "leptons  ️",
                "category": "mindmap",
                "note": "",
                "author": "",
                "score": {
                  "up": 0,
                  "down": 0
                }
              }
            ],
            "author": ""
          },
          {
            "text": "neutrinos  ️",
            "nodes": [],
            "resources": [
              {
                "url": "/physics/particle-physics/elementary-particles/neutrino",
                "text": "neutrinos  ️",
                "category": "mindmap",
                "note": "",
                "author": "",
                "score": {
                  "up": 0,
                  "down": 0
                }
              }
            ],
            "author": ""
          },
          {
            "text": "Higgs boson  ️",
            "nodes": [],
            "resources": [
              {
                "url": "/physics/particle-physics/elementary-particles/higgs-boson",
                "text": "Higgs boson  ️",
                "category": "mindmap",
                "note": "",
                "author": "",
                "score": {
                  "up": 0,
                  "down": 0
                }
              }
            ],
            "author": ""
          },
          {
            "text": "quarks  ️",
            "nodes": [],
            "resources": [
              {
                "url": "/physics/particle-physics/elementary-particles/quarks",
                "text": "quarks  ️",
                "category": "mindmap",
                "note": "",
                "author": "",
                "score": {
                  "up": 0,
                  "down": 0
                }
              }
            ],
            "author": ""
          }
        ],
        "resources": [
          {
            "url": "http://zamalik.weebly.com/uploads/5/6/1/9/56198443/%5Bgriffiths_d.%5D_introduction_to_elementary_particle.pdf",
            "text": "1. introduction to elementary particles",
            "category": "free book",
            "note": "",
            "author": "",
            "score": {
              "up": 0,
              "down": 0
            }
          }
        ],
        "author": ""
      }
    ],
    "resources": [
      {
        "url": "http://www.wikiwand.com/en/Elementary_particle",
        "text": "elementary particles",
        "category": "wiki",
        "note": "",
        "author": "",
        "score": {
          "up": 0,
          "down": 0
        }
      }
    ],
    "author": ""
  }
}