{"token":"pSNmmv1BT87tTufm4gb8vQiWBLsix9L33AuzNfX6","title":"learn anything - network science","backgroundColor":"rgba(243, 246, 243, 1.0)","nodes":[{"allowNodeStrokeColorVariants":false,"decreasingStrokeWidth":true,"foldedSubnodes":false,"isLeftAligned":false,"id":"F9E747F4-C1B0-403A-AFA5-4A1CDEB40209","pathStyle":{"lineType":"curved","strokeStyle":{"color":"rgba(21, 122, 150, 1.0)","dash":null,"width":4.0}},"shapeStyle":{"fillColor":"rgba(255, 255, 255, 1.0)","shapeType":"roundedrect","borderStrokeStyle":{"color":"rgba(246, 246, 246, 1.0)","dash":null,"width":2.0}},"image":null,"title":{"allowToShrinkWidth":true,"maxWidth":300.0,"text":"\u003cp style=\"text-align: center; \"\u003e\u003ca style='color: rgba(22, 103, 132, 1.000000); font: 21px \"Helvetica Neue\";  ' href=\"http://www.wikiwand.com/en/Network_science\" rel=\"nofollow\"\u003enetwork science \u003c/a\u003e\u003ca style='color: rgba(22, 103, 132, 1.000000); font: 21px \"Apple Color Emoji\";  ' href=\"http://www.wikiwand.com/en/Network_science\" rel=\"nofollow\"\u003e🌐\u003c/a\u003e\u003c/p\u003e","fontStyle":null},"note":{"visibleOnCanvas":false,"text":"\u003cp style='color: rgba(0, 0, 0, 1.000000); font: 15px \"Helvetica Neue\";  '\u003eif you think this can be improved in any way\u003c/p\u003e\u003cp\u003e\u003c/p\u003e\u003cp\u003e\u003ca style='color: rgba(0, 0, 0, 1.000000); font: 15px \"Helvetica Neue\";  ' href=\"https://github.com/nikitavoloboev/learn-anything/issues/831\" rel=\"nofollow\"\u003eplease say\u003c/a\u003e\u003cspan style='color: rgba(0, 0, 0, 1.000000); font: 15px \"Helvetica Neue\";  '\u003e \u003c/span\u003e\u003cspan style='color: rgba(0, 0, 0, 1.000000); font: 15px \"Apple Color Emoji\";  '\u003e💙\u003c/span\u003e\u003c/p\u003e"},"noteIndicatorColor":"rgba(21, 122, 150, 1.0)","nodes":[],"location":{"x":320.13873936364257,"y":-442.51661250411917},"layoutStyle":"defaultright","task":null},{"allowNodeStrokeColorVariants":false,"decreasingStrokeWidth":true,"foldedSubnodes":false,"isLeftAligned":false,"id":"86A22BA2-B6E3-46CC-9EB2-8AE8D7644296","pathStyle":{"lineType":"curved","strokeStyle":{"color":"rgba(21, 122, 150, 1.0)","dash":null,"width":4.0}},"shapeStyle":{"fillColor":"rgba(255, 255, 255, 1.0)","shapeType":"roundedrect","borderStrokeStyle":{"color":"rgba(246, 246, 246, 1.0)","dash":null,"width":2.0}},"image":null,"title":{"allowToShrinkWidth":true,"maxWidth":300.0,"text":"\u003cp style=\"text-align: center; \"\u003e\u003ca style='color: rgba(22, 103, 132, 1.000000); font: 21px \"Helvetica Neue\";  ' href=\"http://www.wikiwand.com/en/Semantic_network\" rel=\"nofollow\"\u003esemantic networks \u003c/a\u003e\u003ca style='color: rgba(22, 103, 132, 1.000000); font: 21px \"Apple Color Emoji\";  ' href=\"http://www.wikiwand.com/en/Semantic_network\" rel=\"nofollow\"\u003e🌐\u003c/a\u003e\u003c/p\u003e","fontStyle":null},"note":null,"noteIndicatorColor":"rgba(0, 0, 0, 1.0)","nodes":[],"location":{"x":634.7532778047128,"y":-241.56943841874232},"layoutStyle":"defaultright","task":null},{"allowNodeStrokeColorVariants":false,"decreasingStrokeWidth":true,"foldedSubnodes":false,"isLeftAligned":false,"id":"159ACE83-004F-4C56-AE65-1D9BB800D663","pathStyle":{"lineType":"curved","strokeStyle":{"color":"rgba(21, 122, 150, 1.0)","dash":null,"width":4.0}},"shapeStyle":{"fillColor":"rgba(255, 255, 255, 1.0)","shapeType":"roundedrect","borderStrokeStyle":{"color":"rgba(246, 246, 246, 1.0)","dash":null,"width":2.0}},"image":null,"title":{"allowToShrinkWidth":true,"maxWidth":300.0,"text":"\u003cp style=\"text-align: center; \"\u003e\u003ca style='color: rgba(22, 103, 132, 1.000000); font: 21px \"Helvetica Neue\";  ' href=\"http://www.wikiwand.com/en/Biological_network\" rel=\"nofollow\"\u003ebiological networks \u003c/a\u003e\u003ca style='color: rgba(22, 103, 132, 1.000000); font: 21px \"Apple Color Emoji\";  ' href=\"http://www.wikiwand.com/en/Biological_network\" rel=\"nofollow\"\u003e🌐\u003c/a\u003e\u003c/p\u003e","fontStyle":null},"note":null,"noteIndicatorColor":"rgba(0, 0, 0, 1.0)","nodes":[],"location":{"x":385.1254653930664,"y":-239.40916442871094},"layoutStyle":"defaultright","task":null},{"allowNodeStrokeColorVariants":false,"decreasingStrokeWidth":true,"foldedSubnodes":false,"isLeftAligned":false,"id":"E113B176-EF89-4341-9A40-95E04EC16DDB","pathStyle":{"lineType":"curved","strokeStyle":{"color":"rgba(21, 122, 150, 1.0)","dash":null,"width":4.0}},"shapeStyle":{"fillColor":"rgba(255, 255, 255, 1.0)","shapeType":"roundedrect","borderStrokeStyle":{"color":"rgba(246, 246, 246, 1.0)","dash":null,"width":2.0}},"image":null,"title":{"allowToShrinkWidth":true,"maxWidth":300.0,"text":"\u003cp style=\"text-align: center; \"\u003e\u003ca style='color: rgba(22, 103, 132, 1.000000); font: 21px \"Helvetica Neue\";  ' href=\"/id/NMjhSs88CAGYpxwsd4CP8mkzMRj5o42CMtDVJhtN\" rel=\"nofollow\"\u003ecomputer networking \u003c/a\u003e\u003ca style='color: rgba(22, 103, 132, 1.000000); font: 21px \"Apple Color Emoji\";  ' href=\"/id/NMjhSs88CAGYpxwsd4CP8mkzMRj5o42CMtDVJhtN\" rel=\"nofollow\"\u003e🗺️\u003c/a\u003e\u003c/p\u003e","fontStyle":null},"note":{"visibleOnCanvas":false,"text":"\u003cp style='color: rgba(0, 0, 0, 1.000000); font: 15px \"Helvetica Neue\";  '\u003ecomputer network is a telecommunications network which allows nodes to share resources\u003c/p\u003e\u003cp\u003e\u003c/p\u003e\u003cp style='color: rgba(0, 0, 0, 1.000000); font: 15px \"Helvetica Neue\";  '\u003ein computer networks, networked computing devices exchange data with each other using a data link\u003c/p\u003e"},"noteIndicatorColor":"rgba(21, 122, 150, 1.0)","nodes":[],"location":{"x":-267.9644584655762,"y":-238.89255905151367},"layoutStyle":"defaultright","task":null},{"allowNodeStrokeColorVariants":false,"decreasingStrokeWidth":true,"foldedSubnodes":false,"isLeftAligned":false,"id":"F58C7C88-7181-4442-98AE-ED6037A6C528","pathStyle":{"lineType":"curved","strokeStyle":{"color":"rgba(21, 122, 150, 1.0)","dash":null,"width":4.0}},"shapeStyle":{"fillColor":"rgba(255, 255, 255, 1.0)","shapeType":"roundedrect","borderStrokeStyle":{"color":"rgba(246, 246, 246, 1.0)","dash":null,"width":2.0}},"image":null,"title":{"allowToShrinkWidth":true,"maxWidth":300.0,"text":"\u003cp style=\"text-align: center; \"\u003e\u003ca style='color: rgba(22, 103, 132, 1.000000); font: 21px \"Helvetica Neue\";  ' href=\"http://www.wikiwand.com/en/Complex_network\" rel=\"nofollow\"\u003ecomplex networks \u003c/a\u003e\u003ca style='color: rgba(22, 103, 132, 1.000000); font: 21px \"Apple Color Emoji\";  ' href=\"http://www.wikiwand.com/en/Complex_network\" rel=\"nofollow\"\u003e🌐\u003c/a\u003e\u003c/p\u003e","fontStyle":null},"note":null,"noteIndicatorColor":"rgba(0, 0, 0, 1.0)","nodes":[],"location":{"x":1123.8419867235634,"y":-238.6139091394025},"layoutStyle":"defaultright","task":null},{"allowNodeStrokeColorVariants":false,"decreasingStrokeWidth":true,"foldedSubnodes":false,"isLeftAligned":false,"id":"1C5F70A4-67C2-417A-B2A3-BBBD9DF5D49C","pathStyle":{"lineType":"curved","strokeStyle":{"color":"rgba(21, 122, 150, 1.0)","dash":null,"width":4.0}},"shapeStyle":{"fillColor":"rgba(255, 255, 255, 1.0)","shapeType":"roundedrect","borderStrokeStyle":{"color":"rgba(246, 246, 246, 1.0)","dash":null,"width":2.0}},"image":null,"title":{"allowToShrinkWidth":true,"maxWidth":300.0,"text":"\u003cp style=\"text-align: center; \"\u003e\u003ca style='color: rgba(22, 103, 132, 1.000000); font: 21px \"Helvetica Neue\";  ' href=\"/id/qsGxmY5KYwWw49yFyMMxNmRfszs8swqCEiWg77D1\" rel=\"nofollow\"\u003enetwork topology \u003c/a\u003e\u003ca style='color: rgba(22, 103, 132, 1.000000); font: 21px \"Apple Color Emoji\";  ' href=\"/id/qsGxmY5KYwWw49yFyMMxNmRfszs8swqCEiWg77D1\" rel=\"nofollow\"\u003e🗺️\u003c/a\u003e\u003c/p\u003e","fontStyle":null},"note":null,"noteIndicatorColor":"rgba(0, 0, 0, 1.0)","nodes":[],"location":{"x":-515.0338027330214,"y":-238.56880738913338},"layoutStyle":"defaultright","task":null},{"allowNodeStrokeColorVariants":false,"decreasingStrokeWidth":true,"foldedSubnodes":false,"isLeftAligned":false,"id":"2C0CFADF-444F-4DBA-88A3-1F918D0876BE","pathStyle":{"lineType":"curved","strokeStyle":{"color":"rgba(21, 122, 150, 1.0)","dash":null,"width":4.0}},"shapeStyle":{"fillColor":"rgba(255, 255, 255, 1.0)","shapeType":"roundedrect","borderStrokeStyle":{"color":"rgba(246, 246, 246, 1.0)","dash":null,"width":2.0}},"image":null,"title":{"allowToShrinkWidth":true,"maxWidth":300.0,"text":"\u003cp style=\"text-align: center; \"\u003e\u003ca style='color: rgba(22, 103, 132, 1.000000); font: 21px \"Helvetica Neue\";  ' href=\"http://www.wikiwand.com/en/Social_network\" rel=\"nofollow\"\u003esocial networks \u003c/a\u003e\u003ca style='color: rgba(22, 103, 132, 1.000000); font: 21px \"Apple Color Emoji\";  ' href=\"http://www.wikiwand.com/en/Social_network\" rel=\"nofollow\"\u003e🌐\u003c/a\u003e\u003c/p\u003e","fontStyle":null},"note":null,"noteIndicatorColor":"rgba(0, 0, 0, 1.0)","nodes":[],"location":{"x":900.0078448043721,"y":-238.14142365092619},"layoutStyle":"defaultright","task":null},{"allowNodeStrokeColorVariants":false,"decreasingStrokeWidth":true,"foldedSubnodes":false,"isLeftAligned":false,"id":"BCDAF59C-9383-4232-A833-A0E8125BF80A","pathStyle":{"lineType":"curved","strokeStyle":{"color":"rgba(21, 122, 150, 1.0)","dash":null,"width":4.0}},"shapeStyle":{"fillColor":"rgba(255, 255, 255, 1.0)","shapeType":"roundedrect","borderStrokeStyle":{"color":"rgba(246, 246, 246, 1.0)","dash":null,"width":2.0}},"image":null,"title":{"allowToShrinkWidth":false,"maxWidth":323.0,"text":"\u003cp style=\"text-align: center; \"\u003e\u003ca style='color: rgba(22, 103, 132, 1.000000); font: 21px \"Helvetica Neue\";  ' href=\"http://www.wikiwand.com/en/Telecommunications_network\" rel=\"nofollow\"\u003etelecommunications networks \u003c/a\u003e\u003ca style='color: rgba(22, 103, 132, 1.000000); font: 21px \"Apple Color Emoji\";  ' href=\"http://www.wikiwand.com/en/Telecommunications_network\" rel=\"nofollow\"\u003e🌐\u003c/a\u003e\u003c/p\u003e","fontStyle":null},"note":null,"noteIndicatorColor":"rgba(0, 0, 0, 1.0)","nodes":[],"location":{"x":26.032459259033203,"y":-237.5531234741211},"layoutStyle":"defaultright","task":null}],"connections":[{"endNodeID":"E113B176-EF89-4341-9A40-95E04EC16DDB","startNodeID":"F9E747F4-C1B0-403A-AFA5-4A1CDEB40209","pathStyle":{"lineType":"curved","strokeStyle":{"color":"rgba(254, 90, 46, 1.0)","dash":[5,2],"width":2.0}},"arrowStyle":{"startArrow":null,"endArrow":"trianglefilled"},"title":{"allowToShrinkWidth":true,"maxWidth":250.0,"text":"","fontStyle":{"bold":false,"italic":false,"underline":false,"strikethrough":false,"color":"rgba(255, 255, 255, 1.0)","fontName":"HelveticaNeue","fontSize":14,"alignment":"center"}},"wayPointOffset":{"x":-290.051,"y":100.562}},{"endNodeID":"BCDAF59C-9383-4232-A833-A0E8125BF80A","startNodeID":"F9E747F4-C1B0-403A-AFA5-4A1CDEB40209","pathStyle":{"lineType":"curved","strokeStyle":{"color":"rgba(254, 90, 46, 1.0)","dash":[5,2],"width":2.0}},"arrowStyle":{"startArrow":null,"endArrow":"trianglefilled"},"title":{"allowToShrinkWidth":true,"maxWidth":250.0,"text":"","fontStyle":{"bold":false,"italic":false,"underline":false,"strikethrough":false,"color":"rgba(255, 255, 255, 1.0)","fontName":"HelveticaNeue","fontSize":14,"alignment":"center"}},"wayPointOffset":{"x":-126.303,"y":101.232}},{"endNodeID":"159ACE83-004F-4C56-AE65-1D9BB800D663","startNodeID":"F9E747F4-C1B0-403A-AFA5-4A1CDEB40209","pathStyle":{"lineType":"curved","strokeStyle":{"color":"rgba(254, 90, 46, 1.0)","dash":[5,2],"width":2.0}},"arrowStyle":{"startArrow":null,"endArrow":"trianglefilled"},"title":{"allowToShrinkWidth":true,"maxWidth":250.0,"text":"","fontStyle":{"bold":false,"italic":false,"underline":false,"strikethrough":false,"color":"rgba(255, 255, 255, 1.0)","fontName":"HelveticaNeue","fontSize":14,"alignment":"center"}},"wayPointOffset":{"x":38.7434,"y":101.554}},{"endNodeID":"86A22BA2-B6E3-46CC-9EB2-8AE8D7644296","startNodeID":"F9E747F4-C1B0-403A-AFA5-4A1CDEB40209","pathStyle":{"lineType":"curved","strokeStyle":{"color":"rgba(254, 90, 46, 1.0)","dash":[5,2],"width":2.0}},"arrowStyle":{"startArrow":null,"endArrow":"trianglefilled"},"title":{"allowToShrinkWidth":true,"maxWidth":250.0,"text":"","fontStyle":{"bold":false,"italic":false,"underline":false,"strikethrough":false,"color":"rgba(255, 255, 255, 1.0)","fontName":"HelveticaNeue","fontSize":14,"alignment":"center"}},"wayPointOffset":{"x":163.058,"y":100.474}},{"endNodeID":"2C0CFADF-444F-4DBA-88A3-1F918D0876BE","startNodeID":"F9E747F4-C1B0-403A-AFA5-4A1CDEB40209","pathStyle":{"lineType":"curved","strokeStyle":{"color":"rgba(254, 90, 46, 1.0)","dash":[5,2],"width":2.0}},"arrowStyle":{"startArrow":null,"endArrow":"trianglefilled"},"title":{"allowToShrinkWidth":true,"maxWidth":250.0,"text":"","fontStyle":{"bold":false,"italic":false,"underline":false,"strikethrough":false,"color":"rgba(255, 255, 255, 1.0)","fontName":"HelveticaNeue","fontSize":14,"alignment":"center"}},"wayPointOffset":{"x":287.935,"y":102.188}},{"endNodeID":"F58C7C88-7181-4442-98AE-ED6037A6C528","startNodeID":"F9E747F4-C1B0-403A-AFA5-4A1CDEB40209","pathStyle":{"lineType":"curved","strokeStyle":{"color":"rgba(254, 90, 46, 1.0)","dash":[5,2],"width":2.0}},"arrowStyle":{"startArrow":null,"endArrow":"trianglefilled"},"title":{"allowToShrinkWidth":true,"maxWidth":250.0,"text":"","fontStyle":{"bold":false,"italic":false,"underline":false,"strikethrough":false,"color":"rgba(255, 255, 255, 1.0)","fontName":"HelveticaNeue","fontSize":14,"alignment":"center"}},"wayPointOffset":{"x":406.352,"y":101.952}},{"endNodeID":"1C5F70A4-67C2-417A-B2A3-BBBD9DF5D49C","startNodeID":"F9E747F4-C1B0-403A-AFA5-4A1CDEB40209","pathStyle":{"lineType":"curved","strokeStyle":{"color":"rgba(254, 90, 46, 1.0)","dash":[5,2],"width":2.0}},"arrowStyle":{"startArrow":null,"endArrow":"trianglefilled"},"title":{"allowToShrinkWidth":true,"maxWidth":250.0,"text":"","fontStyle":{"bold":false,"italic":false,"underline":false,"strikethrough":false,"color":"rgba(255, 255, 255, 1.0)","fontName":"HelveticaNeue","fontSize":14,"alignment":"center"}},"wayPointOffset":{"x":-470.873,"y":85.5903}}],"ready":true}