[{"name":"3d printing","map":"computer-hardware---3d-printing"},{"name":"a-frame virtual reality framework","map":"virtual-reality---aframe"},{"name":"abiogenesis","map":"biology---abiogenesis"},{"name":"acting","map":"art---acting"},{"name":"alfred macOS launcher","map":"software---tooling---productivity---alfred"},{"name":"algebra","map":"mathematics---algebra"},{"name":"algorithms","map":"computer-science---algorithms"},{"name":"analysis","map":"mathematics---analysis"},{"name":"android","map":"operating-systems---android"},{"name":"animals","map":"biology---organisms---animals"},{"name":"animation","map":"art---animation"},{"name":"anthropology","map":"anthropology"},{"name":"anything","map":"learn-anything"},{"name":"architecture","map":"architecture"},{"name":"art","map":"art"},{"name":"artificial intelligence","map":"artificial-intelligence"},{"name":"backend development","map":"web-development---backend"},{"name":"bash shell","map":"operating-systems---unix---shells---bash"},{"name":"bezier curves","map":"computer-graphics---bezier-curves"},{"name":"biochemistry","map":"chemistry---biochemistry"},{"name":"bioinformatics","map":"biology---bioinformatics"},{"name":"biology","map":"biology"},{"name":"brain computer interface","map":"neuroscience---brain-computer-interface"},{"name":"browsers","map":"web-development---browsers"},{"name":"c programming language","map":"programming-languages---c"},{"name":"c++ programming language","map":"programming-languages---c--"},{"name":"calculus","map":"mathematics---calculus"},{"name":"category theory","map":"mathematics---category-theory"},{"name":"chaos theory","map":"mathematics---chaos-theory"},{"name":"chemistry","map":"chemistry"},{"name":"classical mechanics","map":"physics---classical-mechanics"},{"name":"clojure programming language","map":"programming---programming-languages---clojure"},{"name":"cognition","map":"cognitive-science---cognition"},{"name":"combinatorics","map":"mathematics---combinatorics"},{"name":"command line tools","map":"software---tooling---cli"},{"name":"competitive programming","map":"programming---competitive-programming"},{"name":"compilers","map":"computer-science---compilers"},{"name":"computability theory","map":"mathematics---computability-theory"},{"name":"computer graphics","map":"computer-graphics"},{"name":"computer hardware","map":"computer-hardware"},{"name":"computer networking","map":"computer-networking"},{"name":"computer science","map":"computer-science"},{"name":"computer vision","map":"computer-vision"},{"name":"consciousness","map":"philosophy---philosophy-of-mind---consciousness"},{"name":"astronomy","map":"space-science---astronomy"},{"name":"creative coding","map":"art---creative-coding"},{"name":"cryptocurrency","map":"cryptocurrency"},{"name":"cryptography","map":"cryptography"},{"name":"css","map":"web-development---front-end---css"},{"name":"data structures","map":"computer-science---data-structures"},{"name":"databases","map":"databases"},{"name":"deep learning","map":"machine-learning---deep-learning"},{"name":"design languages","map":"design---design-languages"},{"name":"design","map":"design"},{"name":"discrete math","map":"mathematics---discrete"},{"name":"diseases","map":"medicine---diseases"},{"name":"distributed computing","map":"distributed-computing"},{"name":"drawing","map":"art---drawing"},{"name":"drugs","map":"chemistry---drugs"},{"name":"economics","map":"economics"},{"name":"electrical engineering","map":"engineering---electrical-engineering"},{"name":"electron","map":"web-development---javascript-libraries---electron"},{"name":"elixir programming language","map":"programming---programming-languages---elixir"},{"name":"elm programming language","map":"programming---programming-languages---elm"},{"name":"emacs text editor","map":"software---tooling---text-editors---emacs"},{"name":"engineering","map":"engineering"},{"name":"english language","map":"linguistics---languages---english"},{"name":"entrepreneurship","map":"entrepreneurship"},{"name":"environmental science","map":"enviromental-science"},{"name":"ergodic theory","map":"mathematics---ergodic-theory"},{"name":"erlang programming language","map":"programming---programming-languages---erlang"},{"name":"ethereum","map":"distributed-computing---ethereum"},{"name":"evolution","map":"biology---evolution"},{"name":"filmmaking","map":"art---filmmaking"},{"name":"financial independence","map":"economics---personal-finance---financial-independence"},{"name":"fish shell","map":"operating-systems---unix---shells---fish"},{"name":"fitness","map":"health---fitness"},{"name":"front end development","map":"web-development---front-end"},{"name":"full stack web development","map":"web-development---full-stack"},{"name":"functional programming","map":"programming---programming-paradigms---functional-programming"},{"name":"game development","map":"game-development"},{"name":"generative art","map":"art---generative-art"},{"name":"genetics","map":"biology---genetics"},{"name":"geometry","map":"mathematics---geometry"},{"name":"git version control","map":"programming---version-control---git"},{"name":"version control","map":"programming---version-control"},{"name":"go programming language","map":"programming---programming-languages---go"},{"name":"godot game engine","map":"game-development---game-engines---godot"},{"name":"graph theory","map":"mathematics---graph-theory"},{"name":"graphic design","map":"design---graphic-design"},{"name":"group theory","map":"mathematics---algebra---abstract-algebra---algebraic-structures---groups---group-theory"},{"name":"haskell programming language","map":"programming---programming-languages---haskell"},{"name":"health","map":"health"},{"name":"history","map":"history"},{"name":"html","map":"web-development---front-end---html"},{"name":"http","map":"computer-networking---protocols---http"},{"name":"idris programming language","map":"programming---programming-languages---idris"},{"name":"industrial design","map":"design---industrial-design"},{"name":"infrastructure","map":"infrastructure"},{"name":"internet of things","map":"computer-networking---internet-of-things"},{"name":"investing","map":"economics---investing"},{"name":"iOS","map":"operating-systems---ios"},{"name":"IPFS","map":"computer-networking---protocols---ipfs"},{"name":"java programming language","map":"programming---programming-languages---java"},{"name":"javascript libraries","map":"web-development---javascript-libraries"},{"name":"javascript programming language","map":"programming---programming-languages---javascript"},{"name":"jQuery","map":"web-development---javascript-libraries---jquery"},{"name":"julia programming language","map":"programming---programming-languages---julia"},{"name":"keras library","map":"machine-learning---machine-learning-libraries---keras"},{"name":"kotlin programming language","map":"programming---programming-languages---kotlin"},{"name":"lambda calculus","map":"mathematics---lambda-calculus"},{"name":"languages","map":"linguistics---languages"},{"name":"LaTeX","map":"design---typesetting---latex"},{"name":"law","map":"law"},{"name":"learning","map":"cognitive-science---cognition---learning"},{"name":"linear algebra","map":"mathematics---linear-algebra"},{"name":"linguistics","map":"linguistics"},{"name":"linux distributions","map":"operating-systems---unix---linux---distributions"},{"name":"linux","map":"operating-systems---unix---linux"},{"name":"lisp programming language","map":"programming---programming-languages---lisp"},{"name":"logic","map":"mathematics---logic"},{"name":"LOVE game engine","map":"game-development---game-engines---love"},{"name":"machine learning libraries","map":"machine-learning---machine-learning-libraries"},{"name":"machine learning","map":"machine-learning"},{"name":"macOS","map":"operating-systems---unix---macos"},{"name":"macroeconomics","map":"economics---macroeconomics"},{"name":"management","map":"management"},{"name":"marketing","map":"marketing"},{"name":"mathematics","map":"mathematics"},{"name":"matlab programming language","map":"programming---programming-languages---matlab"},{"name":"medical specialties","map":"medicine---specialties"},{"name":"medicine","map":"medicine"},{"name":"microeconomics","map":"economics---microeconomics-"},{"name":"mindfulness","map":"health---mindfulness"},{"name":"music","map":"art---music"},{"name":"natural language processing","map":"natural-language-processing"},{"name":"networking protocols","map":"computer-networking---protocols"},{"name":"neural networks","map":"machine-learning---neural-networks"},{"name":"neuroscience","map":"neuroscience"},{"name":"nim programming language","map":"programming---programming-languages---nim"},{"name":"node.js","map":"web-development---backend---nodejs"},{"name":"noSQL databases","map":"databases---nosql-databases"},{"name":"nuclear physics","map":"physics---nuclear-physics"},{"name":"nuclear power","map":"enviromental-science---nuclear-power"},{"name":"number theory","map":"mathematics---number-theory"},{"name":"nutrition","map":"health---nutrition"},{"name":"objective c programming language","map":"programming---programming-languages---objective-c"},{"name":"openGL","map":"computer-graphics---opengl"},{"name":"operating systems","map":"operating-systems"},{"name":"organic chemistry","map":"chemistry---organic-chemistry"},{"name":"penetration testing","map":"security---penetration-testing"},{"name":"perl programming language","map":"programming---programming-languages---perl"},{"name":"philosophy of mind","map":"philosophy---philosophy-of-mind"},{"name":"philosophy","map":"philosophy"},{"name":"photography","map":"art---photography"},{"name":"physics","map":"physics"},{"name":"postgreSQL","map":"databases---relational-databases---postgresql"},{"name":"privacy","map":"security---privacy"},{"name":"processing programming language","map":"programming---programming-languages---processing"},{"name":"programming interviews","map":"programming---programming-interview-preparation"},{"name":"programming language design","map":"programming---programming-language-design"},{"name":"programming language theory","map":"computer-science---programming-language-theory"},{"name":"programming languages","map":"programming---programming-languages"},{"name":"programming mastery","map":"programming---programming-mastery"},{"name":"programming paradigms","map":"programming---programming-paradigms"},{"name":"programming","map":"programming"},{"name":"psychology","map":"psychology"},{"name":"public speaking","map":"art---public-speaking"},{"name":"python programming language","map":"programming---programming-languages---python"},{"name":"pytorch library","map":"machine-learning---machine-learning-libraries---pytorch"},{"name":"quantum computing","map":"physics---quantum-mechanics---quantum-computing"},{"name":"quantum mechanics","map":"physics---quantum-mechanics"},{"name":"r programming language","map":"programming---programming-languages---r"},{"name":"rationality","map":"cognitive-science---cognition---rationality"},{"name":"ray tracing","map":"computer-graphics---rendering---ray-tracing"},{"name":"react native","map":"web-development---javascript-libraries---react-native"},{"name":"react.js","map":"web-development---javascript-libraries---react"},{"name":"redis","map":"databases---nosql-databases---redis"},{"name":"regular expressions","map":"computer-science---regular-expressions"},{"name":"reinforcement learning","map":"machine-learning---reinforcement-learning"},{"name":"relational databases","map":"databases---relational-databases"},{"name":"reverse engineering","map":"programming---reverse-engineering"},{"name":"robotics","map":"engineering---robotics"},{"name":"ruby programming language","map":"programming---programming-languages---ruby"},{"name":"russian language","map":"linguistics---languages---russian"},{"name":"rust programming language","map":"programming---programming-languages---rust"},{"name":"scala programming language","map":"programming---programming-languages---scala"},{"name":"search engines","map":"web-development---search-engines"},{"name":"security","map":"security"},{"name":"sentiment analysis","map":"natural-language-processing---sentiment-analysis"},{"name":"set theory","map":"mathematics---set-theory"},{"name":"singing","map":"art---singing"},{"name":"smalltalk programming language","map":"programming---programming-languages---smalltalk"},{"name":"sociology","map":"sociology"},{"name":"software architecture","map":"programming---software-development---software-architecture"},{"name":"software defined networking","map":"computer-networking---software-defined-networking"},{"name":"special relativity","map":"physics---special-relativity"},{"name":"ssh","map":"computer-networking---protocols---ssh"},{"name":"statistics","map":"mathematics---statistics"},{"name":"sublime text editor","map":"software---tooling---text-editors---sublime-text"},{"name":"swift programming language","map":"programming---programming-languages---swift"},{"name":"tcp/ip","map":"computer-networking---protocols---tcp-ip"},{"name":"tensorflow library","map":"machine-learning---machine-learning-libraries---tensorflow"},{"name":"text editors","map":"software---tooling---text-editors"},{"name":"theory of computation","map":"computer-science---computation---theory-of-computation"},{"name":"software","map":"software"},{"name":"torch library","map":"machine-learning---machine-learning-libraries---torch"},{"name":"type theory","map":"mathematics---type-theory"},{"name":"typescript programming language","map":"programming---programming-languages---typescript"},{"name":"typography","map":"design---typography"},{"name":"unity game engine","map":"game-development---game-engines---unity"},{"name":"unix shells","map":"operating-systems---unix---shells"},{"name":"user experience","map":"design---user-experience"},{"name":"user interfaces","map":"design---user-experience"},{"name":"vim text editor","map":"software---tooling---text-editors---vim"},{"name":"virtual reality","map":"virtual-reality"},{"name":"vs code text editor","map":"software---tooling---text-editors---vs-code"},{"name":"vue.js","map":"web-development---javascript-libraries----vuejs"},{"name":"web crawlers","map":"web-development---web-crawlers"},{"name":"web design","map":"web-development---web-design"},{"name":"web development","map":"web-development"},{"name":"web performance","map":"web-development---web-performance"},{"name":"webpack","map":"web-development---javascript-libraries---webpack"},{"name":"WebRTC","map":"computer-networking---protocols---webrtc"},{"name":"WebSockets","map":"computer-networking---protocols---websocket"},{"name":"windows","map":"operating-systems---windows"},{"name":"writing","map":"art---writing"},{"name":"quantum field theory","map":"physics---quantum-mechanics---quantum-field-theory"},{"name":"guitar","map":"art---music---guitar"},{"name":"model theory","map":"mathematics---model-theory"},{"name":"topology","map":"mathematics---topology"},{"name":"knot theory","map":"mathematics---knot-theory"},{"name":"php programming language","map":"programming---programming-languages---php"},{"name":"meteor library","map":"web-development---javascript-libraries---meteor"},{"name":"scikit-learn library","map":"machine-learning---machine-learning-libraries---scikit-learn"},{"name":"redux","map":"web-development---javascript-libraries---redux"},{"name":"django library","map":"web-development---full-stack---django"},{"name":"german language","map":"linguistics---languages---german"},{"name":"chinese language","map":"linguistics---languages---chinese"},{"name":"query languages","map":"programming---query-languages"},{"name":"graphQL","map":"programming---query-languages---graphql"},{"name":"photoshop","map":"design---graphic-design---photoshop"},{"name":"docker","map":"programming---software-development---devops---docker"},{"name":"kubernetes","map":"programming---software-development---devops---kubernetes"},{"name":"aws","map":"programming---software-development---devops---aws"},{"name":"c# programming language","map":"programming---programming-languages---c-sharp"},{"name":"blockchain","map":"databases---blockchain"},{"name":"data science","map":"data-science"},{"name":"apache spark","map":"data-science---data-processing---apache-spark"},{"name":"software design patterns","map":"programming---design-patterns"},{"name":"japanese language","map":"linguistics---languages---japanese"},{"name":"d3.js library","map":"web-development---javascript-libraries---d3js"},{"name":"graph databases","map":"databases---graph-databases"},{"name":"angular 2 framework","map":"web-development---javascript-libraries---angular-2"},{"name":"webGL","map":"computer-graphics---webgl"},{"name":"software development","map":"programming---software-development"},{"name":"DevOps","map":"programming---software-development---devops"},{"name":"laravel web framework","map":"web-development---backend---laravel"},{"name":"computers","map":"computer-hardware---computer"},{"name":"arduino","map":"computer-hardware---arduino"},{"name":"raspberry pi","map":"computer-hardware---raspberry-pi"},{"name":"convolutional neural networks","map":"machine-learning---neural-networks---convolutional-neural-networks"},{"name":"bootstrap","map":"web-development---front-end---bootstrap"},{"name":"spanish language","map":"linguistics---languages---spanish"},{"name":"french language","map":"linguistics---languages---french"},{"name":"dancing","map":"art---dancing"},{"name":"software testing","map":"programming---software-development---software-testing"},{"name":"everything","map":"learn-anything"},{"name":"assembly programming","map":"programming---programming-languages---assembly"},{"name":"WebAssembly","map":"programming---programming-languages---assembly---WebAssembly"},{"name":"open source development","map":"programming---software-development---open-source"},{"name":"information retrieval","map":"data-science---information-retrieval"},{"name":".NET framework","map":"programming---programming-languages---c-sharp---dotnet"},{"name":"nginx server","map":"programming---software-development---devops---nginx"},{"name":"ruby on rails","map":"programming---programming-languages---ruby---ruby-on-rails"},{"name":"ansible automation","map":"programming---software-development---devops---ansible"},{"name":"babel library","map":"web-development---javascript-libraries---babel"},{"name":"games","map":"games"},{"name":"chess","map":"games---board-games---chess"},{"name":"go game","map":"games---board-games---go"},{"name":"test driven development","map":"programming---software-development---software-testing---test-driven-development"},{"name":"mongoDB","map":"databases---nosql-databases---mongodb"},{"name":"unreal game engine","map":"game-development---game-engines---unreal-engine"},{"name":"blender 3d graphics","map":"computer-graphics---3d-modelling---blender"},{"name":"3d modelling","map":"computer-graphics---3d-modelling"},{"name":"piano","map":"art---music---piano"},{"name":"lua programming language","map":"programming---programming-languages---lua"},{"name":"dart programming language","map":"programming---programming-languages---dart"},{"name":"OCaml programming language","map":"programming---programming-languages---ocaml"},{"name":"linux containers","map":"operating-systems---unix---linux---containers"},{"name":"java virtual machine","map":"computer-science---virtual-machines---jvm"},{"name":"virtual machines","map":"computer-science---virtual-machines"},{"name":"Neo4j database","map":"databases---graph-databases---neo4j"},{"name":"bots","map":"software---bots"},{"name":"software tooling","map":"software---tooling"},{"name":"productivity software","map":"software---tooling---productivity"},{"name":"karabiner macOS app","map":"software---tooling---productivity---karabiner"},{"name":"hammerspoon macOS automation","map":"software---tooling---productivity---hammerspoon"},{"name":"markov chains","map":"mathematics---statistics---probability-theory---markov-chains"},{"name":"probabiliy theory","map":"mathematics---statistics---probability-theory"},{"name":"LLVM compiler infrastructure","map":"computer-science---compilers---llvm"},{"name":"computation","map":"computer-science---computation"},{"name":"computational complexity theory","map":"computer-science---computation---theory-of-computation---computational-complexity-theory"},{"name":"concurrency","map":"computer-science---concurrency"},{"name":"control systems","map":"control-systems"},{"name":"spirituality","map":"philosophy---spirituality"},{"name":"buddhism","map":"philosophy---spirituality---buddhism"},{"name":"watchOS","map":"operating-systems---watchOS"},{"name":"tvOS","map":"operating-systems---tvOS"},{"name":"virtual private networks","map":"security---virtual-private-networks"},{"name":"hacking","map":"security---hacking"},{"name":"information security","map":"security---information-security"},{"name":"ethics","map":"philosophy---ethics"},{"name":"startups","map":"entrepreneurship---startups"},{"name":"vulkan graphics api","map":"computer-graphics---vulkan"},{"name":"metal graphics API","map":"computer-graphics---metal"},{"name":"scalable vector graphics","map":"computer-graphics---vector-graphics---scalable-vector-graphics"},{"name":"vector graphics","map":"computer-graphics---vector-graphics"},{"name":"character encoding","map":"computer-science---computation---character-encoding"},{"name":"game consoles","map":"game-development---game-consoles"},{"name":"sonic pi","map":"art---music---sonic-pi"},{"name":"atom text editor","map":"software---tooling---text-editors---atom"},{"name":"earth science","map":"earth-science"},{"name":"geology","map":"earth-science---geology"},{"name":"space science","map":"space-science"},{"name":"recurrent neural networks","map":"machine-learning---neural-networks---recurrent-neural-networks"},{"name":"ketogenic diet","map":"health---nutrition---keto"},{"name":"general relativity","map":"physics---general-relativity"},{"name":"spacetime","map":"physics---general-relativity---spacetime"},{"name":"black holes","map":"physics---general-relativity---spacetime---black-holes"},{"name":"galaxies","map":"space-science---astronomy---universe---galaxies"},{"name":"universe","map":"space-science---astronomy---universe"},{"name":"world history","map":"history---world-history"},{"name":"historical inventions","map":"history---inventions"},{"name":"JSON","map":"computer-science---data-structures---serialisation---json"},{"name":"data serialisation","map":"computer-science---data-structures---serialisation"},{"name":"protocol buffers","map":"computer-science---data-structures---serialisation---protocol-buffers"},{"name":"data visualisation","map":"data-science---data-visualisation"},{"name":"telecommunication","map":"communication---telecommunication"},{"name":"communication","map":"communication"},{"name":"decision making","map":"psychology---decision-making"},{"name":"problem solving","map":"psychology---decision-making---problem-solving"},{"name":"human brain","map":"neuroscience---human-brain"},{"name":"strength training","map":"health---fitness---strength-training"},{"name":"dermatology","map":"medicine---specialties---dermatology"},{"name":"chemical elements","map":"chemistry---chemical-elements"},{"name":"quantum chemistry","map":"chemistry---quantum-chemistry"},{"name":"molecular symmetry","map":"chemistry---molecular-symmetry"},{"name":"psychedelic drugs","map":"chemistry---drugs---psychedelic"},{"name":"nootropics","map":"chemistry---drugs---nootropics"},{"name":"fortran programming language","map":"programming---programming-languages---fortran"},{"name":"racket programming language","map":"programming---programming-languages---racket"},{"name":"prolog programming language","map":"programming---programming-languages---prolog"},{"name":"coq programming language","map":"programming---programming-languages---coq"},{"name":"applescript programming language","map":"programming---programming-languages---applescript"},{"name":"agda programming language","map":"programming---programming-languages---agda"},{"name":"groovy programming language","map":"programming---programming-languages---groovy"},{"name":"d programming language","map":"programming---programming-languages---d"},{"name":"crystal programming language","map":"programming---programming-languages---crystal"},{"name":"companies","map":"economics---business---companies"},{"name":"unix","map":"operating-systems---unix"},{"name":"zsh","map":"operating-systems---unix---shells---zsh"},{"name":"embedded systems","map":"engineering---electrical-engineering---electronics---embedded-systems"},{"name":"forth programming language","map":"programming---programming-languages---forth"},{"name":"typefaces","map":"design---typography---typeface"},{"name":"colour theory","map":"design---colour-theory"},{"name":"material design","map":"design---design-languages---material-design"},{"name":"arch linux","map":"operating-systems---unix---linux---distributions---arch"},{"name":"fuchsia OS","map":"operating-systems---fuchsia"},{"name":"DNA","map":"biology---genetics---dna"},{"name":"human development","map":"biology---human-development"},{"name":"bitcoin","map":"cryptocurrency---bitcoin"},{"name":"serverless computing","map":"distributed-computing---serverless-computing"},{"name":"google cloud","map":"programming---software-development---devops---google-cloud"},{"name":"microsoft azure","map":"programming---software-development---devops---azure"},{"name":"sports","map":"health---fitness---sports"},{"name":"reasonML","map":"programming---programming-languages---ocaml---reasonml"},{"name":"time series databases","map":"databases---time-series-databases"},{"name":"apache cassandra","map":"databases---nosql-databases---cassandra"},{"name":"mySQL","map":"databases---relational-databases---mysql"},{"name":"SQL","map":"programming---programming-languages---sql"},{"name":"geography","map":"geography"},{"name":"countries","map":"geography---countries"},{"name":"travelling","map":"life---travelling"},{"name":"nomadic lifestyle","map":"life---travelling---nomad"},{"name":"digital art","map":"art---digital-art"},{"name":"comics","map":"art---comics"},{"name":"application programming interfaces","map":"programming---api"},{"name":"peer to peer networks","map":"networking---peer-to-peer"},{"name":"network science","map":"network-science"},{"name":"network topology","map":"network-science---network-topology"},{"name":"board games","map":"games---board-games"},{"name":"video games","map":"games---computer-games"},{"name":"card games","map":"games---card"},{"name":"web games","map":"games---web"},{"name":"Xcode","map":"software---tooling---ide---xcode"},{"name":"messaging software","map":"software---tooling---messaging"},{"name":"adversarial machine learning","map":"machine-learning---adversarial"},{"name":"datasets","map":"data-science---big-data---datasets"},{"name":"numpy library","map":"programming---programming-languages---python---python-libraries---numpy"},{"name":"caffe library","map":"machine-learning---machine-learning-libraries---caffe"},{"name":"politics","map":"law---politics"},{"name":"v8 javascript engine","map":"web-development---browsers---v8"},{"name":"selenium testing","map":"programming---software-development---software-testing---test-automation---selenium"},{"name":"static site generators","map":"web-development---static-site-generators"},{"name":"document object model","map":"web-development---dom"},{"name":"web components","map":"web-development---front-end---web-components"},{"name":"web APIs","map":"web-development---web-api"},{"name":"progressive web apps","map":"web-development---progressive-web-apps"},{"name":"site reliability","map":"web-development---site-reliability"},{"name":"internet","map":"computer-networking---internet"},{"name":"chrome browser","map":"web-development---browsers---chrome"},{"name":"safari browser","map":"web-development---browsers---safari"},{"name":"economic systems","map":"economics---economic-systems"},{"name":"capitalism","map":"economics---economic-systems---capitalism"},{"name":"trasport layer security protocol","map":"computer-networking---protocols---tls"},{"name":"RxJS library","map":"web-development---javascript-libraries---rxjs"},{"name":"ember.js library","map":"web-development---javascript-libraries---emberjs"},{"name":"cycle.js library","map":"web-development---javascript-libraries---cyclejs"},{"name":"jest testing library","map":"web-development---javascript-libraries---jest"},{"name":"particle physics","map":"physics---particle-physics"},{"name":"minimalism","map":"health---mindfulness---minimalism"},{"name":"success","map":"entrepreneurship---success"},{"name":"habits","map":"health---mindfulness---habits"},{"name":"creativity","map":"psychology---creativity"},{"name":"microservices","map":"programming---software-development---software-architecture---microservices"},{"name":"F# programming language","map":"programming---programming-languages---f-sharp"},{"name":"research","map":"cognitive-science---cognition---learning---research"},{"name":"cellular automata","map":"mathematics---computability-theory---cellular-automata"},{"name":"fractals","map":"mathematics---geometry---fractals"},{"name":"business","map":"economics---business"},{"name":"terraform","map":"programming---software-development---devops---terraform"},{"name":"automation","map":"control-systems---automation"},{"name":"life","map":"life"},{"name":"cooking","map":"health---nutrition---food---cooking"},{"name":"mathematical finance","map":"economics---mathematical-finance"},{"name":"urban planning","map":"infrastructure---urban-planning"},{"name":"transportation","map":"infrastructure---transportation"},{"name":"solidity programming language","map":"programming---programming-languages---solidity"},{"name":"finding work","map":"life---work"},{"name":"web scraping","map":"web-development---web-scraping"},{"name":"aeroscpace engineering","map":"engineering---aerospace-engineering"},{"name":"rocket science","map":"engineering---aerospace-engineering---rocket-science"},{"name":"astrophysics","map":"space-science---astronomy---astrophysics"},{"name":"search engine optimisation","map":"web-development---search-engine-optimisation"},{"name":"product management","map":"economics---business---product-management"},{"name":"zen","map":"health---mindfulness---zen"},{"name":"new music","map":"art---music---new-music"},{"name":"monads","map":"programming---programming-paradigms---functional-programming---monads"},{"name":"growth hacking","map":"marketing---growth-hacking"},{"name":"big data","map":"data-science---big-data"},{"name":"design thinking","map":"design---design-thinking"},{"name":"string theory","map":"physics---particle-physics---string-theory"},{"name":"CRISPR","map":"biology---genetics---crispr"},{"name":"accounting","map":"economics---accounting"},{"name":"art history","map":"history---art-history"},{"name":"ASP.NET","map":"programming---programming-languages---c-sharp---dotnet---aspnet"},{"name":"seduction","map":"life---relationships---seduction"},{"name":"relationships","map":"life---relationships"},{"name":"python libraries","map":"programming---programming-languages---python---python-libraries"},{"name":"flask library","map":"programming---programming-languages---python---python-libraries---flask"},{"name":"powershell","map":"programming---programming-languages---c-sharp---dotnet---powershell"},{"name":"korean language","map":"linguistics---languages---korean"},{"name":"graphics processing unit","map":"computer-hardware---computer---gpu"},{"name":"CUDA","map":"computer-hardware---computer---gpu---cuda"},{"name":"OpenCL","map":"computer-hardware---computer---gpu---opencl"},{"name":"apache hadoop","map":"data-science---data-processing---apache-hadoop"},{"name":"bayesian statstics","map":"mathematics---statistics---bayesian-statistics"},{"name":"AutoCAD","map":"design---computer-aided-design---autocad"},{"name":"computer-aided design","map":"design---computer-aided-design"},{"name":"encryption","map":"cryptography---encryption"},{"name":"nixOS distro","map":"operating-systems---unix---linux---distributions---nixos"},{"name":"dynamic programmhing","map":"programming---dynamic-programming"},{"name":"quantified self","map":"life---quantified-self"},{"name":"project management","map":"economics---business---project-management"},{"name":"cognitive science","map":"cognitive-science"},{"name":"signal processing","map":"engineering---electrical-engineering---signal-processing"},{"name":"video editing","map":"art---video-editing"},{"name":"personal finance","map":"economics---personal-finance"},{"name":"alfred workflows","map":"software---tooling---productivity---alfred---workflows"},{"name":"poker","map":"games---card---poker"},{"name":"productivity","map":"life---productivity"},{"name":"more","map":"more"},{"name":"courses","map":"more---courses"},{"name":"NewSQL","map":"databases---nosql-databases---newsql"},{"name":"cockroachDB","map":"databases---nosql-databases---newsql---cockroachdb"},{"name":"ukulele","map":"art---music---ukulele"},{"name":"differential calculus","map":"mathematics---calculus---differential-calculus"},{"name":"gardening","map":"life---hobbies---gardening"},{"name":"hobbies","map":"life---hobbies"},{"name":"homotopy type theory","map":"mathematics---type-theory---homotopy-type-theory"},{"name":"genetic algorithms","map":"computer-science---algorithms---genetic-algorithms"},{"name":"sorting algorithms","map":"computer-science---algorithms---sorting"},{"name":"big O notation","map":"computer-science---algorithms---big-O"},{"name":"anatomy","map":"biology---anatomy"},{"name":"logic programming","map":"programming---programming-paradigms---logic-programming"},{"name":"constraint logic programming","map":"programming---programming-paradigms---logic-programming---constraint-logic-programming"},{"name":"IDE","map":"software---tooling---ide"},{"name":"optics","map":"physics---optics"},{"name":"clojurescript","map":"programming---programming-languages---clojure---clojurescript"},{"name":"mathematical optimisation","map":"mathematics---optimisation"},{"name":"addiction","map":"medicine---specialties---psychiatry---mental-disorders---addiction"},{"name":"programming practice","map":"programming---practice"},{"name":"digital video","map":"computer-graphics---digital-video"},{"name":"quantum entanglement","map":"physics---quantum-mechanics---quantum-entanglement"},{"name":"music theory","map":"art---music---music-theory"},{"name":"polish language","map":"linguistics---languages---polish"},{"name":"quantum information","map":"physics---quantum-mechanics---quantum-information"},{"name":"scheme programming language","map":"programming---programming-languages---scheme"},{"name":"meditation","map":"health---mindfulness---meditation"},{"name":"cybersecurity","map":"security---information-security---cybersecurity"},{"name":"knitting","map":"life---hobbies---knitting"},{"name":"discipline","map":"health---mindfulness---discipline"},{"name":"firebase","map":"programming---software-development---devops---firebase"},{"name":"websites","map":"more---websites"},{"name":"vim plugins","map":"software---tooling---text-editors---vim---plugins"},{"name":"recursion","map":"computer-science---recursion"},{"name":"yoga","map":"health---fitness---yoga"},{"name":"fasting","map":"health---nutrition---fasting"},{"name":"rendering","map":"computer-graphics---rendering"},{"name":"italian language","map":"linguistics---languages---italian"},{"name":"game engines","map":"game-development---game-engines"},{"name":"code review","map":"programming---software-development---code-review"},{"name":"youtube channels","map":"more---youtube-channels"},{"name":"orbital mechainics","map":"physics---orbital-mechanics"},{"name":"drums","map":"art---music---drums"},{"name":"arabic language","map":"linguistics---languages---arabic"},{"name":"sleep","map":"neuroscience---human-brain---sleep"},{"name":"lucid dreaming","map":"neuroscience---human-brain---sleep---lucid-dreaming"},{"name":"ES6","map":"programming---programming-languages---javascript---es6"},{"name":"real analysis","map":"mathematics---analysis---real-analysis"},{"name":"complex analysis","map":"mathematics---analysis---complex-analysis"},{"name":"functional analysis","map":"mathematics---analysis---functional-analysis"},{"name":"measure theory","map":"mathematics---analysis---measure-theory"},{"name":"RSA encryption","map":"cryptography---encryption---rsa"},{"name":"basic income","map":"economics---basic-income"},{"name":"veganism","map":"philosophy---ethics---veganism"},{"name":"human rights","map":"law---rights---human-rights"},{"name":"rights","map":"law---rights"},{"name":"OpenCV","map":"computer-vision---opencv"},{"name":"hash tables","map":"computer-science---data-structures---hash-tables"},{"name":"cold war","map":"history---world-history---cold-war"},{"name":"facial recognition","map":"computer-vision---facial-recognition"},{"name":"books","map":"more---books"},{"name":"research papers","map":"more---research-papers"},{"name":"images","map":"more---images"},{"name":"pi constant","map":"mathematics---geometry---pi"},{"name":"trigonometry","map":"mathematics---geometry---trigonometry"},{"name":"music production","map":"art---music---music-production"},{"name":"reactive programming","map":"programming---programming-paradigms---reactive-programming"},{"name":"advertising","map":"marketing---advertising"},{"name":"differential geometry","map":"mathematics---geometry---differential-geometry"},{"name":"blogs","map":"more---blogs"},{"name":"humans","map":"more---humans"},{"name":"algorithmic trading","map":"economics---trading---algorithmic-trading-"},{"name":"ancient history","map":"history---ancient-history"},{"name":"augmented reality","map":"computer-vision---augmented-reality"},{"name":"data analysis","map":"data-science---data-analysis"},{"name":"pandas library","map":"data-science---data-analysis---pandas"},{"name":"aging","map":"biology---human-development---aging"},{"name":"longevity","map":"biology---human-development---longevity"},{"name":"ecology","map":"biology---ecology"},{"name":"literature","map":"art---literature"},{"name":"US history","map":"history---united-states"},{"name":"epistemology","map":"philosophy---epistemology"},{"name":"mandarin chinese","map":"linguistics---languages---chinese---mandarin"},{"name":"woodworking","map":"life---hobbies---woodworking"},{"name":"supply chain management","map":"economics---business---supply-chain-management"},{"name":"algebraic geometry","map":"mathematics---geometry---algebraic-geometry"},{"name":"algebraic topology","map":"mathematics---topology---algebraic-topology"},{"name":"computational topology","map":"mathematics---topology---computational-topology"},{"name":"lie groups","map":"mathematics---algebra---abstract-algebra---algebraic-structures---groups---group-theory---lie-groups"},{"name":"abstract algebra","map":"mathematics---algebra---abstract-algebra"},{"name":"morse theory","map":"mathematics---topology---morse-theory"},{"name":"motivation","map":"cognitive-science---cognition---motivation"},{"name":"physiology","map":"biology---physiology"},{"name":"emotions","map":"cognitive-science---cognition---emotions"},{"name":"happiness","map":"cognitive-science---cognition---emotions---happiness"},{"name":"search algorithms","map":"computer-science---algorithms---search"},{"name":"monte carlo tree search","map":"computer-science---algorithms---search---monte-carlo-tree-search"},{"name":"bulgarian language","map":"linguistics---languages---bulgarian"},{"name":"computational neuroscience","map":"neuroscience---computational-neuroscience"},{"name":"dutch language","map":"linguistics---languages---dutch"},{"name":"stream processing","map":"programming---programming-paradigms---stream-processing"},{"name":"apache kafka","map":"programming---programming-paradigms---stream-processing---apache-kafka"},{"name":"norwegian language","map":"linguistics---languages---norwegian"},{"name":"tmux","map":"software---tooling---productivity---tmux"},{"name":"spreadsheets software","map":"software---tooling---spreadsheets"},{"name":"excel software","map":"software---tooling---spreadsheets---excel"},{"name":"weight loss","map":"health---nutrition---weight-loss"},{"name":"visual basic","map":"programming---programming-languages---visual-basic"},{"name":"chef configuration management","map":"programming---software-development---devops---chef"},{"name":"interior design","map":"design---interior-design"},{"name":"differential topology","map":"mathematics---topology---differential-topology"},{"name":"music genres","map":"art---music---music-genres"},{"name":"jazz","map":"art---music---music-genres---jazz"},{"name":"classical music","map":"art---music---music-genres---classical"},{"name":"sketch app","map":"design---graphic-design---sketch"},{"name":"reddit subreddits","map":"more---reddit"},{"name":"quora communities","map":"more---quora"},{"name":"boolean logic","map":"mathematics---algebra---boolean-algebra"},{"name":"juggling","map":"health---fitness---sports---juggling"},{"name":"three.js","map":"web-development---javascript-libraries---threejs"},{"name":"botany","map":"biology---botany"},{"name":"adobe illustrator","map":"design---graphic-design---adobe-illustrator"},{"name":"space architecture","map":"architecture---space-architecture"},{"name":"java libraries","map":"programming---programming-languages---java---java-libraries"},{"name":"spark web framework","map":"programming---programming-languages---java---java-libraries---spark"},{"name":"spring framework","map":"programming---programming-languages---java---java-libraries---spring"},{"name":"content management systems","map":"web-development---content-management-systems"},{"name":"wordpress","map":"web-development---content-management-systems---wordpress"},{"name":"drupal","map":"web-development---content-management-systems---drupal"},{"name":"object oriented programming","map":"programming---programming-paradigms---object-oriented"},{"name":"pixel art","map":"art---digital-art---pixel-art"},{"name":"greek language","map":"linguistics---languages---greek"},{"name":"multivariable calculus","map":"mathematics---calculus---multivariable-calculus"},{"name":"tensors","map":"mathematics---geometry---tensors"},{"name":"molecular biology","map":"chemistry---biochemistry---molecular-biology"},{"name":"football","map":"health---fitness---sports---football"},{"name":"skateboarding","map":"health---fitness---sports---skateboarding"},{"name":"basketball","map":"health---fitness---sports---basketball"},{"name":"surfing","map":"health---fitness---sports---surfing"},{"name":"archery","map":"health---fitness---sports---archery"},{"name":"western philosophy","map":"philosophy---western-philosophy"},{"name":"stoicism","map":"philosophy---western-philosophy---stoicism"},{"name":"functions","map":"mathematics---algebra---functions"},{"name":"probabilistic graphical models","map":"mathematics---statistics---statistical-model---probabilistic-graphical-models"},{"name":"convex optimisation","map":"mathematics---optimisation---convex-optimisation"},{"name":"gradient descent","map":"mathematics---optimisation---gradient-descent"},{"name":"statistical model","map":"mathematics---statistics---statistical-model"},{"name":"model selection","map":"mathematics---statistics---statistical-model---model-selection"},{"name":"bayesian inference","map":"mathematics---statistics---bayesian-statistics---bayesian-inference"},{"name":"bayesian machine learning","map":"mathematics---statistics---bayesian-statistics---bayesian-machine-learning"},{"name":"unsupervised learning","map":"machine-learning---unsupervised-learning"},{"name":"general artificial intelligence","map":"artificial-intelligence---general-artificial-intelligence"},{"name":"AI planning","map":"artificial-intelligence---ai-planning"},{"name":"computational physics","map":"physics---computational-physics"},{"name":"monte carlo methods","map":"physics---computational-physics---monte-carlo-methods"},{"name":"particle filters","map":"physics---computational-physics---monte-carlo-methods---particle-filters"},{"name":"Kalman filter","map":"physics---computational-physics---monte-carlo-methods---kalman-filter"},{"name":"dynamical systems","map":"mathematics---dynamical-system"},{"name":"data anonymisation","map":"security---information-security---sanitisation"},{"name":"AlphaGo","map":"machine-learning---deep-learning---alphago"},{"name":"autonomous driving","map":"machine-learning---deep-learning---autonomous-driving"},{"name":"integration","map":"mathematics---calculus---integration"},{"name":"laplace transform","map":"mathematics---calculus---integral-transform---laplace-transform"},{"name":"new movies","map":"art---filmmaking---new-movies"},{"name":"debian linux","map":"operating-systems---unix---linux---distributions---debian"},{"name":"keyboards","map":"computer-hardware---computer---keyboards"},{"name":"mechanical keyboards","map":"computer-hardware---computer---keyboards---mechanical-keyboards"},{"name":"Sass","map":"web-development---front-end---css---sass"},{"name":"test automation","map":"programming---software-development---software-testing---test-automation"},{"name":"martial arts","map":"art---martial-arts"},{"name":"computational biology","map":"biology---computational-biology"},{"name":"social psychology","map":"psychology---social-psychology"},{"name":"sketching","map":"art---drawing---sketching"},{"name":"REST api","map":"programming---api---rest"},{"name":"draft.js","map":"web-development---javascript-libraries---draftjs"},{"name":"ESLint","map":"web-development---javascript-libraries---eslint"},{"name":"Ajax","map":"web-development---ajax"},{"name":"apple frameworks","map":"programming---programming-languages---swift---apple-frameworks"},{"name":"macOS apps","map":"operating-systems---unix---macos---apps"},{"name":"jxa","map":"operating-systems---unix---macos---jxa"},{"name":"eigenvectors","map":"mathematics---linear-algebra---eigenvectors"},{"name":"automated theory proving","map":"mathematics---logic---automated-theorem-proving"},{"name":"Godels incompleteness theorem","map":"mathematics---logic---godels-incompleteness-theorem"},{"name":"software licenses","map":"law---software-licenses"},{"name":"human memory","map":"neuroscience---human-brain---memories"},{"name":"neurolinguistics","map":"neuroscience---human-brain---neurolinguistics"},{"name":"elementary particles","map":"physics---particle-physics---elementary-particles"},{"name":"Higgs boson","map":"physics---particle-physics---elementary-particles---higgs-boson"},{"name":"primordial black holes","map":"physics---general-relativity---spacetime---black-holes---primordial-black-holes"},{"name":"thermodynamics","map":"physics---thermodynamics"},{"name":"andromeda galaxy","map":"space-science---astronomy---universe---galaxies---andromeda"},{"name":"milky way galaxy","map":"space-science---astronomy---universe---galaxies---milky-way"},{"name":"solar system","map":"space-science---astronomy---universe---galaxies---milky-way---solar-system"},{"name":"the sun","map":"space-science---astronomy---universe---galaxies---milky-way---solar-system---sun"},{"name":"virtualisation","map":"computer-hardware---virtualisation"},{"name":"web applications","map":"software---web-applications"},{"name":"web accessibility","map":"web-development---web-design---web-accessibility"},{"name":"progressive enhancement","map":"web-development---web-design---progressive-enhancement"},{"name":"jekyll","map":"web-development---static-site-generators---jekyll"},{"name":"hugo","map":"web-development---static-site-generators---hugo"},{"name":"DMT","map":"chemistry---drugs---psychedelic---dmt"},{"name":"MDMA","map":"chemistry---drugs---psychedelic---mdma"},{"name":"LSD","map":"chemistry---drugs---psychedelic---lsd"},{"name":"CoreML","map":"programming---programming-languages---swift---apple-frameworks---coreML"},{"name":"podcasts","map":"more---podcasts"},{"name":"vert.x","map":"computer-science---virtual-machines---jvm---vertx"},{"name":"RxJava","map":"computer-science---virtual-machines---jvm---rxjava"},{"name":"neurology","map":"medicine---neurology"},{"name":"hebrew language","map":"linguistics---languages---hebrew"},{"name":"normal distribution","map":"mathematics---statistics---probability-theory---distributions---normal-distribution"},{"name":"Taylor series","map":"mathematics---calculus---series---taylor-series"},{"name":"Eulers formula","map":"mathematics---analysis---complex-analysis---eulers-formula"},{"name":"space filling curves","map":"mathematics---analysis---space-filling-curve"},{"name":"quadtree data structure","map":"computer-science---data-structures---quadtree"},{"name":"array data structure","map":"computer-science---data-structures---arrays"},{"name":"linked list data structure","map":"computer-science---data-structures---linked-lists"},{"name":"N-body simulation","map":"mathematics---dynamical-system---n-body-simulation"},{"name":"docker swarm","map":"programming---software-development---devops---docker---docker-swarm"},{"name":"Hilbert curve","map":"mathematics---geometry---fractals---hilbert-curve"},{"name":"turing completeness","map":"mathematics---computability-theory---turing-completeness"},{"name":"halting problem","map":"mathematics---computability-theory---turing-completeness---halting-problem"},{"name":"proof theory","map":"mathematics---logic---proof-theory"},{"name":"uncertainty principle","map":"physics---quantum-mechanics---uncertainty-principle"},{"name":"condensed matter physics","map":"physics---condensed-matter-physics"},{"name":"viml","map":"software---tooling---text-editors---vim---viml"},{"name":"zero-knowledge proofs","map":"cryptography---zero-knowledge-proofs"},{"name":"metaphysics","map":"philosophy---philosophy-of-mind---metaphysics"},{"name":"phenomenology","map":"philosophy---philosophy-of-mind---phenomenology"},{"name":"physicalism","map":"philosophy---philosophy-of-mind---physicalism"},{"name":"feedforward neural network","map":"machine-learning---neural-networks---feedforward-neural-network"},{"name":"ASP.NET Core","map":"programming---programming-languages---c-sharp---dotnet---aspnet---aspnet-core"},{"name":"carpentry","map":"life---hobbies---carpentry"},{"name":"computational geometry","map":"mathematics---geometry---computational-geometry"},{"name":"polymer physics","map":"physics---polymer-physics"},{"name":"volume rendering","map":"computer-graphics---volume-rendering"},{"name":"electromagnetism","map":"physics---electromagnetism"},{"name":"magnets","map":"physics---electromagnetism---magnet"},{"name":"Lorentz force","map":"physics---electromagnetism---lorentz-force"},{"name":"optical character recognition","map":"computer-vision---optical-character-recognition"},{"name":"state of matter","map":"physics---continuum-mechanics---state-of-matter"},{"name":"continuum mechanics","map":"physics---continuum-mechanics"},{"name":"Wayland protocol","map":"operating-systems---unix---linux---wayland"},{"name":"central processing unit","map":"computer-hardware---computer---cpu"},{"name":"computer memory","map":"computer-hardware---computer---computer-memory"},{"name":"random access memory","map":"computer-hardware---computer---computer-memory---random-access-memory"},{"name":"online advertising","map":"marketing---advertising---online-advertising"},{"name":"styled components","map":"web-development---front-end---css---styled-components"},{"name":"jenkins","map":"programming---software-development---devops---jenkins"},{"name":"pricing","map":"economics---business---pricing"},{"name":"risk management","map":"economics---business---risk-management"},{"name":"spring boot","map":"programming---programming-languages---java---java-libraries---spring---spring-boot"},{"name":"elasticsearch","map":"web-development---search-engines---elasticsearch"},{"name":"apache solr","map":"web-development---search-engines---solr"},{"name":"information mapping","map":"cognitive-science---cognition---learning---information-mapping"},{"name":"decision tree learning","map":"machine-learning---decision-tree-learning"},{"name":"statistical classification","map":"machine-learning---pattern-recognition---statistical-classification"},{"name":"matrix factorisation","map":"mathematics---linear-algebra---matrices---matrix-factorisation"},{"name":"non-negative matrix factorisation","map":"mathematics---linear-algebra---matrices---matrix-factorisation---non-negative-matrix-factorisation"},{"name":"random forests","map":"machine-learning---pattern-recognition---statistical-classification---random-forests"},{"name":"mind maps","map":"cognitive-science---cognition---learning---information-mapping---mind-maps"},{"name":"data mining","map":"data-science---data-mining"},{"name":"polygon mesh","map":"computer-graphics---polygon-mesh"},{"name":"geometry processing","map":"computer-graphics---polygon-mesh---geometry-processing"},{"name":"coreOS","map":"operating-systems---unix---linux---distributions---coreos"},{"name":"transfer learning","map":"machine-learning---deep-learning---transfer-learning"},{"name":"pointers","map":"computer-hardware---computer---computer-memory---pointers"},{"name":"memory management","map":"computer-hardware---computer---computer-memory---memory-management"},{"name":"garbage collection","map":"computer-hardware---computer---computer-memory---memory-management---garbage-collection"},{"name":"grunt task runner","map":"web-development---javascript-libraries---grunt"},{"name":"build automation","map":"programming---software-development---build-automation"},{"name":"Gradle","map":"programming---software-development---build-automation---gradle"},{"name":"love","map":"cognitive-science---cognition---emotions---love"},{"name":"electronics","map":"engineering---electrical-engineering---electronics"},{"name":"hardware description languages","map":"engineering---electrical-engineering---electronics---hardware-description-languages"},{"name":"Verilog","map":"engineering---electrical-engineering---electronics---hardware-description-languages---verilog"},{"name":"VHDL","map":"engineering---electrical-engineering---electronics---hardware-description-languages---vhdl"},{"name":"world building","map":"art---world-building"},{"name":"digital marketing","map":"marketing---digital-marketing"},{"name":"MXNet","map":"machine-learning---machine-learning-libraries---mxnet"},{"name":"representation theory","map":"mathematics---algebra---abstract-algebra---representation-theory"},{"name":"x86 architecture","map":"programming---programming-languages---assembly---x86"},{"name":"ARM architecture","map":"programming---programming-languages---assembly---arm"},{"name":"morphology","map":"linguistics---morphology"},{"name":"backpropagation","map":"machine-learning---neural-networks---backpropagation"},{"name":"electromagnetic field","map":"physics---electromagnetism---electromagnetic-field"},{"name":"mathematical models","map":"mathematics---mathematical-models"},{"name":"game theory","map":"mathematics---mathematical-models---game-theory"},{"name":"evolutionary game theory","map":"mathematics---mathematical-models---game-theory---evolutionary-game-theory"},{"name":"information geometry","map":"mathematics---geometry---information-geometry"},{"name":"swedish language","map":"linguistics---languages---swedish"},{"name":"anime","map":"art---anime"},{"name":"manga","map":"art---comics---manga"},{"name":"Gaussian processes","map":"mathematics---statistics---statistical-model---gaussian-process"},{"name":"regression analysis","map":"mathematics---statistics---regression-analysis"},{"name":"generalised linear models","map":"mathematics---statistics---regression-analysis---linear-regression---generalised-linear-models"},{"name":"irish language","map":"linguistics---languages---irish"},{"name":"FPGA","map":"engineering---electrical-engineering---electronics---fpga"},{"name":"data processing","map":"data-science---data-processing"},{"name":"song writing","map":"art---music---song-writing"},{"name":"turkish language","map":"linguistics---languages---turkish"},{"name":"cluster analysis","map":"data-science---data-mining---cluster-analysis"},{"name":"analog electronics","map":"engineering---electrical-engineering---electronics---analog-electronics"},{"name":"MapReduce","map":"data-science---data-processing---mapreduce"},{"name":"naive set theory","map":"mathematics---set-theory---naive-set-theory"},{"name":"Russels paradox","map":"mathematics---set-theory---naive-set-theory---russells-paradox"},{"name":"dependent type theory","map":"mathematics---type-theory---dependent-type-theory"},{"name":"Curry-Howard correspondence","map":"mathematics---logic---proof-theory---curry-howard-correspondence"},{"name":"electrochemistry","map":"chemistry---electrochemistry"},{"name":"Nash equilibrium","map":"mathematics---mathematical-models---game-theory---nash-equilibrium"},{"name":"distributed denial of service","map":"security---information-security---cybersecurity---ddos"},{"name":"nuclear astrophysics","map":"space-science---astronomy---astrophysics---nuclear-astrophysics"},{"name":"differential forms","map":"mathematics---calculus---multivariable-calculus---differential-form"},{"name":"Lebesgue Integration","map":"mathematics---calculus---integration---lebesgue-integration"},{"name":"kung fu","map":"art---martial-arts---kung-fu"},{"name":"snowboarding","map":"health---fitness---sports---snowboarding"},{"name":"portuguese language","map":"linguistics---languages---portuguese"},{"name":"pattern recognition","map":"machine-learning---pattern-recognition"},{"name":"linear discriminant analysis","map":"machine-learning---pattern-recognition---linear-discriminant-analysis"},{"name":"econometrics","map":"economics---econometrics"},{"name":"time series analysis","map":"data-science---data-analysis---time-series-analysis"},{"name":"brainfuck programming language","map":"programming---programming-languages---brainfuck"},{"name":"psychiatry","map":"medicine---specialties---psychiatry"},{"name":"mental disorders","map":"medicine---specialties---psychiatry---mental-disorders"},{"name":"anxiety","map":"medicine---specialties---psychiatry---mental-disorders---anxiety"},{"name":"depression","map":"medicine---specialties---psychiatry---mental-disorders---depression"},{"name":"calligraphy","map":"art---calligraphy"},{"name":"generative adversarial networks","map":"machine-learning---neural-networks---generative-adversarial-networks"},{"name":"mechanical engineering","map":"engineering---mechanical-engineering"},{"name":"computer architecture","map":"computer-hardware---computer---computer-architecture"},{"name":"kernel","map":"operating-systems---kernel"},{"name":"image processing","map":"computer-graphics---image-processing"},{"name":"cognitive psychology","map":"psychology---cognitive-psychology"},{"name":"image kernels","map":"computer-graphics---image-processing---image-kernels"},{"name":"mechatronics","map":"engineering---mechatronics"},{"name":"electromagnetic radiation","map":"physics---electromagnetism---electromagnetic-radiation"},{"name":"light","map":"physics---electromagnetism---electromagnetic-radiation---light"},{"name":"Gaussian elimination","map":"mathematics---linear-algebra---gaussian-elimination"},{"name":"redshift","map":"physics---electromagnetism---electromagnetic-radiation---redshift"},{"name":"energy","map":"physics---energy"},{"name":"algebraic data types","map":"mathematics---type-theory---algebraic-data-types"},{"name":"vibration","map":"physics---classical-mechanics---vibration"},{"name":"sound","map":"physics---classical-mechanics---vibration---sound"},{"name":"periodic functions","map":"mathematics---algebra---functions---periodic-functions"},{"name":"shaders","map":"computer-graphics---shaders"},{"name":"conditional random fields","map":"mathematics---statistics---statistical-model---conditional-random-fields"},{"name":"behavioural economics","map":"economics---behavioural-economics"},{"name":"chemical engineering","map":"engineering---chemical-engineering"},{"name":"immunology","map":"biology---immunology"},{"name":"gravity","map":"physics---classical-mechanics---gravity"},{"name":"quantum gravity","map":"physics---quantum-mechanics---quantum-gravity"},{"name":"loop quantum gravity","map":"physics---quantum-mechanics---quantum-gravity---loop-quantum-gravity"},{"name":"linear regression","map":"mathematics---statistics---regression-analysis---linear-regression"},{"name":"closures","map":"computer-science---programming-language-theory---closures"},{"name":"monoids","map":"mathematics---algebra---abstract-algebra---algebraic-structures---monoids"},{"name":"motion graphics","map":"art---animation---motion-graphics"},{"name":"adobe after effects","map":"art---animation---motion-graphics---after-effects"},{"name":"analytics","map":"data-science---data-analysis---analytics"},{"name":"predictive analytics","map":"data-science---data-analysis---analytics---predictive-analytics"},{"name":"affiliate marketing","map":"marketing---affiliate-marketing"},{"name":"ARKit","map":"programming---programming-languages---swift---apple-frameworks---arkit"},{"name":"javascript promises","map":"programming---programming-languages---javascript---promises"},{"name":"constrained optimisation","map":"mathematics---optimisation---constrained-optimisation"},{"name":"ordinary differential equations","map":"mathematics---calculus---differential-calculus---ordinary-differential-equations"},{"name":"multiple integrals","map":"mathematics---calculus---integration---multiple-integrals"},{"name":"surface integrals","map":"mathematics---calculus---integration---multiple-integrals---surface-integrals"},{"name":"time management","map":"life---productivity---time-management"},{"name":"trading","map":"economics---trading"},{"name":"stock exchange","map":"economics---trading---stock-exchange"},{"name":"quantitative trading","map":"economics---trading"},{"name":"czech language","map":"linguistics---languages---czech"},{"name":"probability distributions","map":"mathematics---statistics---probability-theory---distributions"},{"name":"binomial distributions","map":"mathematics---statistics---probability-theory---distributions---binomial-distribution"},{"name":"Pareto distribution","map":"mathematics---statistics---probability-theory---distributions---pareto-distribution"},{"name":"Bernoulli distribution","map":"mathematics---statistics---probability-theory---distributions---bernoulli-distribution"},{"name":"Poisson distribution","map":"mathematics---statistics---probability-theory---distributions---poisson-distribution"},{"name":"fluid mechanics","map":"physics---continuum-mechanics---fluid-mechanics"},{"name":"autohotkey","map":"operating-systems---windows---autohotkey"},{"name":"windows server","map":"operating-systems---windows---windows-server"},{"name":"active directory","map":"operating-systems---windows---windows-server---active-directory"},{"name":"electronic components","map":"engineering---electrical-engineering---electronics---electronic-components"},{"name":"semiconductor devices","map":"engineering---electrical-engineering---electronics---electronic-components---semiconductor-devices"},{"name":"transistors","map":"engineering---electrical-engineering---electronics---electronic-components---semiconductor-devices---transistor"},{"name":"express.js","map":"web-development---javascript-libraries---express"},{"name":"biological cells","map":"biology---organisms---cells"},{"name":"stem cells","map":"biology---organisms---cells---stem-cells"},{"name":"binary search trees","map":"computer-science---data-structures---binary-search-trees"},{"name":"neutrino particles","map":"physics---particle-physics---elementary-particles---neutrino"},{"name":"symfony framework","map":"programming---programming-languages---php---symfony"},{"name":"light fields","map":"physics---electromagnetism---electromagnetic-radiation---light---light-field"},{"name":"mathematical series","map":"mathematics---calculus---series"},{"name":"geometric series","map":"mathematics---calculus---series---geometric-series"},{"name":"arithmetic","map":"mathematics---number-theory---arithmetic"},{"name":"hearthstone","map":"games---video-games---hearthstone"},{"name":"dota 2","map":"games---video-games---dota-2"},{"name":"GitHub","map":"programming---version-control---git---github"},{"name":"just-in-time compilation","map":"computer-science---compilers---just-in-time-compilation"},{"name":"systemd","map":"operating-systems---unix---linux---systemd"},{"name":"algebraic structures","map":"mathematics---algebra---abstract-algebra---algebraic-structures"},{"name":"groups","map":"mathematics---algebra---abstract-algebra---algebraic-structures---groups"},{"name":"rings","map":"mathematics---algebra---abstract-algebra---algebraic-structures---rings"},{"name":"modules","map":"mathematics---algebra---abstract-algebra---algebraic-structures---modules"},{"name":"lattices","map":"mathematics---algebra---abstract-algebra---algebraic-structures---lattices"},{"name":"vectors","map":"mathematics---linear-algebra---vectors"},{"name":"vector spaces","map":"mathematics---linear-algebra---vectors---vector-space"},{"name":"homomorphism","map":"mathematics---algebra---abstract-algebra---homomorphism"},{"name":"isomorphism","map":"mathematics---algebra---abstract-algebra---homomorphism---isomorphism"},{"name":"flow type checking","map":"programming---programming-languages---javascript---flow"},{"name":"control theory","map":"engineering---control-theory"},{"name":"responsive web design","map":"web-development---web-design---responsive-web-development"},{"name":"food","map":"health---nutrition---food"},{"name":"smoothies","map":"health---nutrition---smoothies"},{"name":"aws lambda","map":"programming---software-development---devops---aws---aws-lambda"},{"name":"golf","map":"health---fitness---sports---golf"},{"name":"matrices","map":"mathematics---linear-algebra---matrices"},{"name":"dot product","map":"mathematics---linear-algebra---vectors---dot-product"},{"name":"cross product","map":"mathematics---linear-algebra---vectors---cross-product"},{"name":"determinants","map":"mathematics---linear-algebra---matrices---determinants"},{"name":"rank of a matrix","map":"mathematics---linear-algebra---matrices---rank"},{"name":"semigroups","map":"mathematics---algebra---abstract-algebra---algebraic-structures---groups---semigroups"},{"name":"transformations","map":"mathematics---algebra---functions---transformations"},{"name":"rank of a matrix","map":"mathematics---linear-algebra---matrices---rank"},{"name":"linear transformations","map":"mathematics---algebra---functions---transformations---linear-transformations"},{"name":"red-black trees","map":"computer-science---data-structures---red-black-trees"},{"name":"affine transformations","map":"mathematics---algebra---functions---transformations---affine-transformations"},{"name":"singular value decomposition","map":"mathematics---linear-algebra---matrices---singular-value-decomposition"},{"name":"meaning of life","map":"life---meaning-of-life"},{"name":"google adwords","map":"marketing---advertising---google-adwords"},{"name":"agile software development","map":"programming---software-development---agile-software-development"},{"name":"Scrum","map":"programming---software-development---agile-software-development---scrum"},{"name":"supervised learning","map":"machine-learning---supervised-learning"},{"name":"support vector machines","map":"machine-learning---supervised-learning---support-vector-machines"},{"name":"documentaries","map":"more---documentaries"}]